{"dataset": "ms_reps_unsolved", "linked_dataset": "1190MS", "words": ["Y", "y", "YY", "yy", "YYY", "yyy", "YYYY", "yyyy", "yxYX", "yxyX", "XYxY", "XYxy", "YYYYY", "yyyyy", "yyxYX", "yyxyX", "yxYYX", "yxyyX", "YxYXY", "YxyXY", "yXYxY", "yXYxy", "yxYXY", "yxYXy", "yxyXY", "yxyXy", "XYYxY", "XYYxy", "XYxYY", "XYxyy", "YYYYYY", "yyyyyy", "yyyxYX", "yyyxyX", "yyxYYX", "yyxyyX", "yyXYxY", "yyXYxy", "yyxYXY", "yyxYXy", "yyxyXY", "yyxyXy", "yxYYYX", "yxyyyX", "YXYYxY", "YXYYxy", "YxYYXY", "YxyyXY", "yXYYxY", "yXYYxy", "yxYYXY", "yxYYXy", "yxyyXY", "yxyyXy", "YxYXYY", "YxyXYY", "yXYxYY", "yXYxyy", "yxYXYY", "yxYXyy", "yxyXYY", "yxyXyy", "yxxYXX", "yxxyXX", "XYYYxY", "XYYYxy", "XYYxYY", "XYYxyy", "XYxYYY", "XYxyyy", "XXYxxY", "XXYxxy", "YYYYYYY", "yyyyyyy", "yyyyxYX", "yyyyxyX", "yyyxYYX", "yyyxyyX", "yyyXYxY", "yyyXYxy", "yyyxYXY", "yyyxYXy", "yyyxyXY", "yyyxyXy", "yyxYYYX", "yyxyyyX", "yyXYYxY", "yyXYYxy", "yyxYYXY", "yyxYYXy", "yyxyyXY", "yyxyyXy", "YYxYXYY", "YYxyXYY", "yyXYxYY", "yyXYxyy", "yyxYXYY", "yyxYXyy", "yyxyXYY", "yyxyXyy", "yyxxYXX", "yyxxyXX", "yxYYYYX", "yxyyyyX", "YXYYYxY", "YXYYYxy", "YxYYYXY", "YxyyyXY", "yXYYYxY", "yXYYYxy", "yxYYYXY", "yxYYYXy", "yxyyyXY", "yxyyyXy", "YXYYxYY", "YXYYxyy", "YxYYXYY", "YxyyXYY", "yXYYxYY", "yXYYxyy", "yxYYXYY", "yxYYXyy", "yxyyXYY", "yxyyXyy", "YxYXYYY", "YxyXYYY", "yXYxYYY", "yXYxyyy", "yxYXYYY", "yxYXyyy", "yxyXYYY", "yxyXyyy", "yxYxYXX", "yxYxyXX", "yxyxYXX", "yxyxyXX", "yXYxxYX", "yXYxxyX", "yxxYYXX", "yxxyyXX", "yxxYXYX", "yxxYXyX", "yxxyXYX", "yxxyXyX", "yXXYxxY", "yXXYxxy", "yxxYXXY", "yxxYXXy", "yxxyXXY", "yxxyXXy", "XYYYYxY", "XYYYYxy", "XYYYxYY", "XYYYxyy", "XYYxYYY", "XYYxyyy", "XYxYYYY", "XYxyyyy", "XYXYxxY", "XYXYxxy", "XYxxYXY", "XYxxyXY", "XXYYxxY", "XXYYxxy", "XXYxYxY", "XXYxYxy", "XXYxyxY", "XXYxyxy", "XXYxxYY", "XXYxxyy"], "nvals": [1, 2, 3, 4, 5, 6, 7], "n_trivial": 640, "n_rep_cells": 550, "cells": [{"w": "Y", "n": 1, "status": "trivial", "ms_idx": 1}, {"w": "Y", "n": 2, "status": "trivial", "ms_idx": 171}, {"w": "Y", "n": 3, "status": "trivial", "ms_idx": 309}, {"w": "Y", "n": 4, "status": "trivial", "ms_idx": 407}, {"w": "Y", "n": 5, "status": "trivial", "ms_idx": 459}, {"w": "Y", "n": 6, "status": "trivial", "ms_idx": 494}, {"w": "Y", "n": 7, "status": "trivial", "ms_idx": 518}, {"w": "y", "n": 1, "status": "trivial", "ms_idx": 0}, {"w": "y", "n": 2, "status": "trivial", "ms_idx": 170}, {"w": "y", "n": 3, "status": "trivial", "ms_idx": 308}, {"w": "y", "n": 4, "status": "trivial", "ms_idx": 406}, {"w": "y", "n": 5, "status": "trivial", "ms_idx": 458}, {"w": "y", "n": 6, "status": "trivial", "ms_idx": 493}, {"w": "y", "n": 7, "status": "trivial", "ms_idx": 517}, {"w": "YY", "n": 1, "status": "trivial", "ms_idx": 3}, {"w": "YY", "n": 2, "status": "trivial", "ms_idx": 173}, {"w": "YY", "n": 3, "status": "trivial", "ms_idx": 311}, {"w": "YY", "n": 4, "status": "trivial", "ms_idx": 409}, {"w": "YY", "n": 5, "status": "trivial", "ms_idx": 461}, {"w": "YY", "n": 6, "status": "trivial", "ms_idx": 496}, {"w": "YY", "n": 7, "status": "trivial", "ms_idx": 520}, {"w": "yy", "n": 1, "status": "trivial", "ms_idx": 2}, {"w": "yy", "n": 2, "status": "trivial", "ms_idx": 172}, {"w": "yy", "n": 3, "status": "trivial", "ms_idx": 310}, {"w": "yy", "n": 4, "status": "trivial", "ms_idx": 408}, {"w": "yy", "n": 5, "status": "trivial", "ms_idx": 460}, {"w": "yy", "n": 6, "status": "trivial", "ms_idx": 495}, {"w": "yy", "n": 7, "status": "trivial", "ms_idx": 519}, {"w": "YYY", "n": 1, "status": "trivial", "ms_idx": 5}, {"w": "YYY", "n": 2, "status": "trivial", "ms_idx": 175}, {"w": "YYY", "n": 3, "status": "trivial", "ms_idx": 313}, {"w": "YYY", "n": 4, "status": "trivial", "ms_idx": 411}, {"w": "YYY", "n": 5, "status": "trivial", "ms_idx": 463}, {"w": "YYY", "n": 6, "status": "trivial", "ms_idx": 498}, {"w": "YYY", "n": 7, "status": "trivial", "ms_idx": 522}, {"w": "yyy", "n": 1, "status": "trivial", "ms_idx": 4}, {"w": "yyy", "n": 2, "status": "trivial", "ms_idx": 174}, {"w": "yyy", "n": 3, "status": "trivial", "ms_idx": 312}, {"w": "yyy", "n": 4, "status": "trivial", "ms_idx": 410}, {"w": "yyy", "n": 5, "status": "trivial", "ms_idx": 462}, {"w": "yyy", "n": 6, "status": "trivial", "ms_idx": 497}, {"w": "yyy", "n": 7, "status": "trivial", "ms_idx": 521}, {"w": "YYYY", "n": 1, "status": "trivial", "ms_idx": 11}, {"w": "YYYY", "n": 2, "status": "trivial", "ms_idx": 181}, {"w": "YYYY", "n": 3, "status": "trivial", "ms_idx": 317}, {"w": "YYYY", "n": 4, "status": "trivial", "ms_idx": 415}, {"w": "YYYY", "n": 5, "status": "trivial", "ms_idx": 467}, {"w": "YYYY", "n": 6, "status": "trivial", "ms_idx": 500}, {"w": "YYYY", "n": 7, "status": "trivial", "ms_idx": 524}, {"w": "yyyy", "n": 1, "status": "trivial", "ms_idx": 8}, {"w": "yyyy", "n": 2, "status": "trivial", "ms_idx": 178}, {"w": "yyyy", "n": 3, "status": "trivial", "ms_idx": 315}, {"w": "yyyy", "n": 4, "status": "trivial", "ms_idx": 413}, {"w": "yyyy", "n": 5, "status": "trivial", "ms_idx": 465}, {"w": "yyyy", "n": 6, "status": "trivial", "ms_idx": 499}, {"w": "yyyy", "n": 7, "status": "trivial", "ms_idx": 523}, {"w": "yxYX", "n": 1, "status": "trivial", "ms_idx": 7}, {"w": "yxYX", "n": 2, "status": "trivial", "ms_idx": 177}, {"w": "yxYX", "n": 3, "status": "trivial", "ms_idx": 314}, {"w": "yxYX", "n": 4, "status": "trivial", "ms_idx": 412}, {"w": "yxYX", "n": 5, "status": "trivial", "ms_idx": 464}, {"w": "yxYX", "n": 6, "status": "trivial", "ms_idx": 590}, {"w": "yxYX", "n": 7, "status": "trivial", "ms_idx": 616}, {"w": "yxyX", "n": 1, "status": "trivial", "ms_idx": 6}, {"w": "yxyX", "n": 2, "status": "trivial", "ms_idx": 176}, {"w": "yxyX", "n": 3, "status": "13_1", "ms_idx": 898, "rep_idx": 0}, {"w": "yxyX", "n": 4, "status": "15_1", "ms_idx": 949, "rep_idx": 1}, {"w": "yxyX", "n": 5, "status": "16_1", "ms_idx": 741, "rep_idx": 2}, {"w": "yxyX", "n": 6, "status": "20_8", "ms_idx": 662, "rep_idx": 123}, {"w": "yxyX", "n": 7, "status": "22_13", "ms_idx": 911, "rep_idx": 179}, {"w": "XYxY", "n": 1, "status": "trivial", "ms_idx": 10}, {"w": "XYxY", "n": 2, "status": "trivial", "ms_idx": 180}, {"w": "XYxY", "n": 3, "status": "13_1", "ms_idx": 939, "rep_idx": 0}, {"w": "XYxY", "n": 4, "status": "15_1", "ms_idx": 639, "rep_idx": 1}, {"w": "XYxY", "n": 5, "status": "16_1", "ms_idx": 650, "rep_idx": 2}, {"w": "XYxY", "n": 6, "status": "20_9", "ms_idx": 786, "rep_idx": 124}, {"w": "XYxY", "n": 7, "status": "22_14", "ms_idx": 950, "rep_idx": 180}, {"w": "XYxy", "n": 1, "status": "trivial", "ms_idx": 9}, {"w": "XYxy", "n": 2, "status": "trivial", "ms_idx": 179}, {"w": "XYxy", "n": 3, "status": "trivial", "ms_idx": 316}, {"w": "XYxy", "n": 4, "status": "trivial", "ms_idx": 414}, {"w": "XYxy", "n": 5, "status": "trivial", "ms_idx": 466}, {"w": "XYxy", "n": 6, "status": "trivial", "ms_idx": 591}, {"w": "XYxy", "n": 7, "status": "trivial", "ms_idx": 617}, {"w": "YYYYY", "n": 1, "status": "trivial", "ms_idx": 29}, {"w": "YYYYY", "n": 2, "status": "trivial", "ms_idx": 199}, {"w": "YYYYY", "n": 3, "status": "trivial", "ms_idx": 329}, {"w": "YYYYY", "n": 4, "status": "trivial", "ms_idx": 423}, {"w": "YYYYY", "n": 5, "status": "trivial", "ms_idx": 469}, {"w": "YYYYY", "n": 6, "status": "trivial", "ms_idx": 502}, {"w": "YYYYY", "n": 7, "status": "trivial", "ms_idx": 526}, {"w": "yyyyy", "n": 1, "status": "trivial", "ms_idx": 20}, {"w": "yyyyy", "n": 2, "status": "trivial", "ms_idx": 190}, {"w": "yyyyy", "n": 3, "status": "trivial", "ms_idx": 323}, {"w": "yyyyy", "n": 4, "status": "trivial", "ms_idx": 419}, {"w": "yyyyy", "n": 5, "status": "trivial", "ms_idx": 468}, {"w": "yyyyy", "n": 6, "status": "trivial", "ms_idx": 501}, {"w": "yyyyy", "n": 7, "status": "trivial", "ms_idx": 525}, {"w": "yyxYX", "n": 1, "status": "trivial", "ms_idx": 19}, {"w": "yyxYX", "n": 2, "status": "trivial", "ms_idx": 189}, {"w": "yyxYX", "n": 3, "status": "13_1", "ms_idx": 818, "rep_idx": 0}, {"w": "yyxYX", "n": 4, "status": "trivial", "ms_idx": 418}, {"w": "yyxYX", "n": 5, "status": "17_31", "ms_idx": 718, "rep_idx": 83}, {"w": "yyxYX", "n": 6, "status": "16_7", "ms_idx": 832, "rep_idx": 128}, {"w": "yyxYX", "n": 7, "status": "21_35", "ms_idx": 860, "rep_idx": 185}, {"w": "yyxyX", "n": 1, "status": "trivial", "ms_idx": 18}, {"w": "yyxyX", "n": 2, "status": "trivial", "ms_idx": 188}, {"w": "yyxyX", "n": 3, "status": "trivial", "ms_idx": 322}, {"w": "yyxyX", "n": 4, "status": "trivial", "ms_idx": 535}, {"w": "yyxyX", "n": 5, "status": "17_30", "ms_idx": 984, "rep_idx": 82}, {"w": "yyxyX", "n": 6, "status": "16_6", "ms_idx": 1136, "rep_idx": 127}, {"w": "yyxyX", "n": 7, "status": "23_22", "ms_idx": 1018, "rep_idx": 184}, {"w": "yxYYX", "n": 1, "status": "trivial", "ms_idx": 17}, {"w": "yxYYX", "n": 2, "status": "trivial", "ms_idx": 187}, {"w": "yxYYX", "n": 3, "status": "trivial", "ms_idx": 321}, {"w": "yxYYX", "n": 4, "status": "14_1", "ms_idx": 1075, "rep_idx": 5}, {"w": "yxYYX", "n": 5, "status": "trivial", "ms_idx": 561}, {"w": "yxYYX", "n": 6, "status": "19_33", "ms_idx": 904, "rep_idx": 126}, {"w": "yxYYX", "n": 7, "status": "19_37", "ms_idx": 756, "rep_idx": 183}, {"w": "yxyyX", "n": 1, "status": "trivial", "ms_idx": 12}, {"w": "yxyyX", "n": 2, "status": "trivial", "ms_idx": 182}, {"w": "yxyyX", "n": 3, "status": "trivial", "ms_idx": 318}, {"w": "yxyyX", "n": 4, "status": "15_10", "ms_idx": 863, "rep_idx": 45}, {"w": "yxyyX", "n": 5, "status": "14_1", "ms_idx": 1100, "rep_idx": 5}, {"w": "yxyyX", "n": 6, "status": "17_34", "ms_idx": 688, "rep_idx": 125}, {"w": "yxyyX", "n": 7, "status": "21_34", "ms_idx": 876, "rep_idx": 181}, {"w": "YxYXY", "n": 1, "status": "trivial", "ms_idx": 28}, {"w": "YxYXY", "n": 2, "status": "trivial", "ms_idx": 198}, {"w": "YxYXY", "n": 3, "status": "13_1", "ms_idx": 640, "rep_idx": 0}, {"w": "YxYXY", "n": 4, "status": "15_1", "ms_idx": 1144, "rep_idx": 1}, {"w": "YxYXY", "n": 5, "status": "16_1", "ms_idx": 893, "rep_idx": 2}, {"w": "YxYXY", "n": 6, "status": "17_1", "ms_idx": 887, "rep_idx": 3}, {"w": "YxYXY", "n": 7, "status": "23_24", "ms_idx": 1008, "rep_idx": 191}, {"w": "YxyXY", "n": 1, "status": "trivial", "ms_idx": 27}, {"w": "YxyXY", "n": 2, "status": "trivial", "ms_idx": 197}, {"w": "YxyXY", "n": 3, "status": "trivial", "ms_idx": 328}, {"w": "YxyXY", "n": 4, "status": "trivial", "ms_idx": 422}, {"w": "YxyXY", "n": 5, "status": "trivial", "ms_idx": 564}, {"w": "YxyXY", "n": 6, "status": "trivial", "ms_idx": 595}, {"w": "YxyXY", "n": 7, "status": "trivial", "ms_idx": 621}, {"w": "yXYxY", "n": 1, "status": "trivial", "ms_idx": 22}, {"w": "yXYxY", "n": 2, "status": "trivial", "ms_idx": 192}, {"w": "yXYxY", "n": 3, "status": "13_1", "ms_idx": 654, "rep_idx": 0}, {"w": "yXYxY", "n": 4, "status": "15_1", "ms_idx": 915, "rep_idx": 1}, {"w": "yXYxY", "n": 5, "status": "16_1", "ms_idx": 1074, "rep_idx": 2}, {"w": "yXYxY", "n": 6, "status": "17_35", "ms_idx": 936, "rep_idx": 129}, {"w": "yXYxY", "n": 7, "status": "21_36", "ms_idx": 890, "rep_idx": 186}, {"w": "yXYxy", "n": 1, "status": "trivial", "ms_idx": 21}, {"w": "yXYxy", "n": 2, "status": "trivial", "ms_idx": 191}, {"w": "yXYxy", "n": 3, "status": "trivial", "ms_idx": 324}, {"w": "yXYxy", "n": 4, "status": "trivial", "ms_idx": 420}, {"w": "yXYxy", "n": 5, "status": "trivial", "ms_idx": 562}, {"w": "yXYxy", "n": 6, "status": "trivial", "ms_idx": 594}, {"w": "yXYxy", "n": 7, "status": "trivial", "ms_idx": 620}, {"w": "yxYXY", "n": 1, "status": "trivial", "ms_idx": 16}, {"w": "yxYXY", "n": 2, "status": "trivial", "ms_idx": 186}, {"w": "yxYXY", "n": 3, "status": "trivial", "ms_idx": 320}, {"w": "yxYXY", "n": 4, "status": "trivial", "ms_idx": 417}, {"w": "yxYXY", "n": 5, "status": "trivial", "ms_idx": 560}, {"w": "yxYXY", "n": 6, "status": "trivial", "ms_idx": 593}, {"w": "yxYXY", "n": 7, "status": "trivial", "ms_idx": 619}, {"w": "yxYXy", "n": 1, "status": "trivial", "ms_idx": 15}, {"w": "yxYXy", "n": 2, "status": "trivial", "ms_idx": 185}, {"w": "yxYXy", "n": 3, "status": "trivial", "ms_idx": 319}, {"w": "yxYXy", "n": 4, "status": "trivial", "ms_idx": 416}, {"w": "yxYXy", "n": 5, "status": "trivial", "ms_idx": 559}, {"w": "yxYXy", "n": 6, "status": "trivial", "ms_idx": 592}, {"w": "yxYXy", "n": 7, "status": "trivial", "ms_idx": 618}, {"w": "yxyXY", "n": 1, "status": "trivial", "ms_idx": 14}, {"w": "yxyXY", "n": 2, "status": "trivial", "ms_idx": 184}, {"w": "yxyXY", "n": 3, "status": "13_1", "ms_idx": 954, "rep_idx": 0}, {"w": "yxyXY", "n": 4, "status": "15_1", "ms_idx": 882, "rep_idx": 1}, {"w": "yxyXY", "n": 5, "status": "16_1", "ms_idx": 646, "rep_idx": 2}, {"w": "yxyXY", "n": 6, "status": "17_1", "ms_idx": 713, "rep_idx": 3}, {"w": "yxyXY", "n": 7, "status": "21_1", "ms_idx": 642, "rep_idx": 4}, {"w": "yxyXy", "n": 1, "status": "trivial", "ms_idx": 13}, {"w": "yxyXy", "n": 2, "status": "trivial", "ms_idx": 183}, {"w": "yxyXy", "n": 3, "status": "13_1", "ms_idx": 1060, "rep_idx": 0}, {"w": "yxyXy", "n": 4, "status": "15_1", "ms_idx": 805, "rep_idx": 1}, {"w": "yxyXy", "n": 5, "status": "16_1", "ms_idx": 1065, "rep_idx": 2}, {"w": "yxyXy", "n": 6, "status": "20_8", "ms_idx": 1149, "rep_idx": 123}, {"w": "yxyXy", "n": 7, "status": "23_21", "ms_idx": 1093, "rep_idx": 182}, {"w": "XYYxY", "n": 1, "status": "trivial", "ms_idx": 26}, {"w": "XYYxY", "n": 2, "status": "trivial", "ms_idx": 196}, {"w": "XYYxY", "n": 3, "status": "trivial", "ms_idx": 327}, {"w": "XYYxY", "n": 4, "status": "trivial", "ms_idx": 536}, {"w": "XYYxY", "n": 5, "status": "17_33", "ms_idx": 711, "rep_idx": 85}, {"w": "XYYxY", "n": 6, "status": "16_9", "ms_idx": 1038, "rep_idx": 133}, {"w": "XYYxY", "n": 7, "status": "23_23", "ms_idx": 702, "rep_idx": 190}, {"w": "XYYxy", "n": 1, "status": "trivial", "ms_idx": 25}, {"w": "XYYxy", "n": 2, "status": "trivial", "ms_idx": 195}, {"w": "XYYxy", "n": 3, "status": "13_1", "ms_idx": 716, "rep_idx": 0}, {"w": "XYYxy", "n": 4, "status": "trivial", "ms_idx": 421}, {"w": "XYYxy", "n": 5, "status": "17_32", "ms_idx": 678, "rep_idx": 84}, {"w": "XYYxy", "n": 6, "status": "16_8", "ms_idx": 1114, "rep_idx": 132}, {"w": "XYYxy", "n": 7, "status": "21_38", "ms_idx": 728, "rep_idx": 189}, {"w": "XYxYY", "n": 1, "status": "trivial", "ms_idx": 24}, {"w": "XYxYY", "n": 2, "status": "trivial", "ms_idx": 194}, {"w": "XYxYY", "n": 3, "status": "trivial", "ms_idx": 326}, {"w": "XYxYY", "n": 4, "status": "15_11", "ms_idx": 1145, "rep_idx": 46}, {"w": "XYxYY", "n": 5, "status": "14_1", "ms_idx": 891, "rep_idx": 5}, {"w": "XYxYY", "n": 6, "status": "17_36", "ms_idx": 888, "rep_idx": 131}, {"w": "XYxYY", "n": 7, "status": "21_37", "ms_idx": 1007, "rep_idx": 188}, {"w": "XYxyy", "n": 1, "status": "trivial", "ms_idx": 23}, {"w": "XYxyy", "n": 2, "status": "trivial", "ms_idx": 193}, {"w": "XYxyy", "n": 3, "status": "trivial", "ms_idx": 325}, {"w": "XYxyy", "n": 4, "status": "14_1", "ms_idx": 1064, "rep_idx": 5}, {"w": "XYxyy", "n": 5, "status": "trivial", "ms_idx": 563}, {"w": "XYxyy", "n": 6, "status": "19_34", "ms_idx": 807, "rep_idx": 130}, {"w": "XYxyy", "n": 7, "status": "19_38", "ms_idx": 1109, "rep_idx": 187}, {"w": "YYYYYY", "n": 1, "status": "trivial", "ms_idx": 71}, {"w": "YYYYYY", "n": 2, "status": "trivial", "ms_idx": 237}, {"w": "YYYYYY", "n": 3, "status": "trivial", "ms_idx": 357}, {"w": "YYYYYY", "n": 4, "status": "trivial", "ms_idx": 437}, {"w": "YYYYYY", "n": 5, "status": "trivial", "ms_idx": 477}, {"w": "YYYYYY", "n": 6, "status": "trivial", "ms_idx": 506}, {"w": "YYYYYY", "n": 7, "status": "trivial", "ms_idx": 530}, {"w": "yyyyyy", "n": 1, "status": "trivial", "ms_idx": 50}, {"w": "yyyyyy", "n": 2, "status": "trivial", "ms_idx": 218}, {"w": "yyyyyy", "n": 3, "status": "trivial", "ms_idx": 343}, {"w": "yyyyyy", "n": 4, "status": "trivial", "ms_idx": 430}, {"w": "yyyyyy", "n": 5, "status": "trivial", "ms_idx": 473}, {"w": "yyyyyy", "n": 6, "status": "trivial", "ms_idx": 504}, {"w": "yyyyyy", "n": 7, "status": "trivial", "ms_idx": 528}, {"w": "yyyxYX", "n": 1, "status": "trivial", "ms_idx": 49}, {"w": "yyyxYX", "n": 2, "status": "trivial", "ms_idx": 217}, {"w": "yyyxYX", "n": 3, "status": "trivial", "ms_idx": 342}, {"w": "yyyxYX", "n": 4, "status": "15_1", "ms_idx": 1126, "rep_idx": 1}, {"w": "yyyxYX", "n": 5, "status": "17_33", "ms_idx": 1053, "rep_idx": 85}, {"w": "yyyxYX", "n": 6, "status": "trivial", "ms_idx": 599}, {"w": "yyyxYX", "n": 7, "status": "18_9", "ms_idx": 877, "rep_idx": 202}, {"w": "yyyxyX", "n": 1, "status": "trivial", "ms_idx": 48}, {"w": "yyyxyX", "n": 2, "status": "trivial", "ms_idx": 216}, {"w": "yyyxyX", "n": 3, "status": "trivial", "ms_idx": 341}, {"w": "yyyxyX", "n": 4, "status": "trivial", "ms_idx": 539}, {"w": "yyyxyX", "n": 5, "status": "17_32", "ms_idx": 804, "rep_idx": 84}, {"w": "yyyxyX", "n": 6, "status": "trivial", "ms_idx": 598}, {"w": "yyyxyX", "n": 7, "status": "19_40", "ms_idx": 977, "rep_idx": 201}, {"w": "yyxYYX", "n": 1, "status": "trivial", "ms_idx": 47}, {"w": "yyxYYX", "n": 2, "status": "trivial", "ms_idx": 215}, {"w": "yyxYYX", "n": 3, "status": "trivial", "ms_idx": 340}, {"w": "yyxYYX", "n": 4, "status": "trivial", "ms_idx": 429}, {"w": "yyxYYX", "n": 5, "status": "trivial", "ms_idx": 472}, {"w": "yyxYYX", "n": 6, "status": "trivial", "ms_idx": 503}, {"w": "yyxYYX", "n": 7, "status": "trivial", "ms_idx": 527}, {"w": "yyxyyX", "n": 1, "status": "trivial", "ms_idx": 42}, {"w": "yyxyyX", "n": 2, "status": "trivial", "ms_idx": 210}, {"w": "yyxyyX", "n": 3, "status": "trivial", "ms_idx": 337}, {"w": "yyxyyX", "n": 4, "status": "trivial", "ms_idx": 425}, {"w": "yyxyyX", "n": 5, "status": "16_4", "ms_idx": 959, "rep_idx": 88}, {"w": "yyxyyX", "n": 6, "status": "19_35", "ms_idx": 928, "rep_idx": 138}, {"w": "yyxyyX", "n": 7, "status": "20_10", "ms_idx": 695, "rep_idx": 200}, {"w": "yyXYxY", "n": 1, "status": "trivial", "ms_idx": 52}, {"w": "yyXYxY", "n": 2, "status": "trivial", "ms_idx": 220}, {"w": "yyXYxY", "n": 3, "status": "13_1", "ms_idx": 861, "rep_idx": 0}, {"w": "yyXYxY", "n": 4, "status": "15_1", "ms_idx": 1184, "rep_idx": 1}, {"w": "yyXYxY", "n": 5, "status": "16_1", "ms_idx": 844, "rep_idx": 2}, {"w": "yyXYxY", "n": 6, "status": "17_35", "ms_idx": 780, "rep_idx": 129}, {"w": "yyXYxY", "n": 7, "status": "18_6", "ms_idx": 1188, "rep_idx": 196}, {"w": "yyXYxy", "n": 1, "status": "trivial", "ms_idx": 51}, {"w": "yyXYxy", "n": 2, "status": "trivial", "ms_idx": 219}, {"w": "yyXYxy", "n": 3, "status": "trivial", "ms_idx": 344}, {"w": "yyXYxy", "n": 4, "status": "trivial", "ms_idx": 431}, {"w": "yyXYxy", "n": 5, "status": "trivial", "ms_idx": 569}, {"w": "yyXYxy", "n": 6, "status": "trivial", "ms_idx": 600}, {"w": "yyXYxy", "n": 7, "status": "trivial", "ms_idx": 624}, {"w": "yyxYXY", "n": 1, "status": "trivial", "ms_idx": 46}, {"w": "yyxYXY", "n": 2, "status": "trivial", "ms_idx": 214}, {"w": "yyxYXY", "n": 3, "status": "13_1", "ms_idx": 687, "rep_idx": 0}, {"w": "yyxYXY", "n": 4, "status": "trivial", "ms_idx": 428}, {"w": "yyxYXY", "n": 5, "status": "17_31", "ms_idx": 1017, "rep_idx": 83}, {"w": "yyxYXY", "n": 6, "status": "16_7", "ms_idx": 788, "rep_idx": 128}, {"w": "yyxYXY", "n": 7, "status": "21_35", "ms_idx": 842, "rep_idx": 185}, {"w": "yyxYXy", "n": 1, "status": "trivial", "ms_idx": 45}, {"w": "yyxYXy", "n": 2, "status": "trivial", "ms_idx": 213}, {"w": "yyxYXy", "n": 3, "status": "13_1", "ms_idx": 940, "rep_idx": 0}, {"w": "yyxYXy", "n": 4, "status": "trivial", "ms_idx": 427}, {"w": "yyxYXy", "n": 5, "status": "17_31", "ms_idx": 792, "rep_idx": 83}, {"w": "yyxYXy", "n": 6, "status": "16_7", "ms_idx": 1187, "rep_idx": 128}, {"w": "yyxYXy", "n": 7, "status": "21_35", "ms_idx": 895, "rep_idx": 185}, {"w": "yyxyXY", "n": 1, "status": "trivial", "ms_idx": 44}, {"w": "yyxyXY", "n": 2, "status": "trivial", "ms_idx": 212}, {"w": "yyxyXY", "n": 3, "status": "trivial", "ms_idx": 339}, {"w": "yyxyXY", "n": 4, "status": "trivial", "ms_idx": 426}, {"w": "yyxyXY", "n": 5, "status": "17_30", "ms_idx": 813, "rep_idx": 82}, {"w": "yyxyXY", "n": 6, "status": "16_6", "ms_idx": 806, "rep_idx": 127}, {"w": "yyxyXY", "n": 7, "status": "23_22", "ms_idx": 997, "rep_idx": 184}, {"w": "yyxyXy", "n": 1, "status": "trivial", "ms_idx": 43}, {"w": "yyxyXy", "n": 2, "status": "trivial", "ms_idx": 211}, {"w": "yyxyXy", "n": 3, "status": "trivial", "ms_idx": 338}, {"w": "yyxyXy", "n": 4, "status": "trivial", "ms_idx": 538}, {"w": "yyxyXy", "n": 5, "status": "17_30", "ms_idx": 1178, "rep_idx": 82}, {"w": "yyxyXy", "n": 6, "status": "16_6", "ms_idx": 1079, "rep_idx": 127}, {"w": "yyxyXy", "n": 7, "status": "23_22", "ms_idx": 957, "rep_idx": 184}, {"w": "yxYYYX", "n": 1, "status": "trivial", "ms_idx": 41}, {"w": "yxYYYX", "n": 2, "status": "trivial", "ms_idx": 209}, {"w": "yxYYYX", "n": 3, "status": "13_1", "ms_idx": 970, "rep_idx": 0}, {"w": "yxYYYX", "n": 4, "status": "15_10", "ms_idx": 739, "rep_idx": 45}, {"w": "yxYYYX", "n": 5, "status": "trivial", "ms_idx": 471}, {"w": "yxYYYX", "n": 6, "status": "17_38", "ms_idx": 1123, "rep_idx": 137}, {"w": "yxYYYX", "n": 7, "status": "18_8", "ms_idx": 1165, "rep_idx": 199}, {"w": "yxyyyX", "n": 1, "status": "trivial", "ms_idx": 32}, {"w": "yxyyyX", "n": 2, "status": "trivial", "ms_idx": 200}, {"w": "yxyyyX", "n": 3, "status": "trivial", "ms_idx": 330}, {"w": "yxyyyX", "n": 4, "status": "14_1", "ms_idx": 908, "rep_idx": 5}, {"w": "yxyyyX", "n": 5, "status": "trivial", "ms_idx": 470}, {"w": "yxyyyX", "n": 6, "status": "17_37", "ms_idx": 927, "rep_idx": 136}, {"w": "yxyyyX", "n": 7, "status": "19_39", "ms_idx": 694, "rep_idx": 194}, {"w": "YXYYxY", "n": 1, "status": "trivial", "ms_idx": 70}, {"w": "YXYYxY", "n": 2, "status": "trivial", "ms_idx": 236}, {"w": "YXYYxY", "n": 3, "status": "trivial", "ms_idx": 356}, {"w": "YXYYxY", "n": 4, "status": "trivial", "ms_idx": 542}, {"w": "YXYYxY", "n": 5, "status": "17_33", "ms_idx": 789, "rep_idx": 85}, {"w": "YXYYxY", "n": 6, "status": "16_9", "ms_idx": 1036, "rep_idx": 133}, {"w": "YXYYxY", "n": 7, "status": "23_23", "ms_idx": 999, "rep_idx": 190}, {"w": "YXYYxy", "n": 1, "status": "trivial", "ms_idx": 69}, {"w": "YXYYxy", "n": 2, "status": "trivial", "ms_idx": 235}, {"w": "YXYYxy", "n": 3, "status": "13_1", "ms_idx": 1034, "rep_idx": 0}, {"w": "YXYYxy", "n": 4, "status": "trivial", "ms_idx": 436}, {"w": "YXYYxy", "n": 5, "status": "17_32", "ms_idx": 831, "rep_idx": 84}, {"w": "YXYYxy", "n": 6, "status": "16_8", "ms_idx": 935, "rep_idx": 132}, {"w": "YXYYxy", "n": 7, "status": "21_38", "ms_idx": 851, "rep_idx": 189}, {"w": "YxYYXY", "n": 1, "status": "trivial", "ms_idx": 68}, {"w": "YxYYXY", "n": 2, "status": "trivial", "ms_idx": 234}, {"w": "YxYYXY", "n": 3, "status": "trivial", "ms_idx": 355}, {"w": "YxYYXY", "n": 4, "status": "15_11", "ms_idx": 783, "rep_idx": 46}, {"w": "YxYYXY", "n": 5, "status": "14_1", "ms_idx": 1011, "rep_idx": 5}, {"w": "YxYYXY", "n": 6, "status": "17_36", "ms_idx": 760, "rep_idx": 131}, {"w": "YxYYXY", "n": 7, "status": "21_37", "ms_idx": 874, "rep_idx": 188}, {"w": "YxyyXY", "n": 1, "status": "trivial", "ms_idx": 65}, {"w": "YxyyXY", "n": 2, "status": "trivial", "ms_idx": 231}, {"w": "YxyyXY", "n": 3, "status": "trivial", "ms_idx": 353}, {"w": "YxyyXY", "n": 4, "status": "14_1", "ms_idx": 1104, "rep_idx": 5}, {"w": "YxyyXY", "n": 5, "status": "trivial", "ms_idx": 571}, {"w": "YxyyXY", "n": 6, "status": "19_34", "ms_idx": 1013, "rep_idx": 130}, {"w": "YxyyXY", "n": 7, "status": "20_12", "ms_idx": 1052, "rep_idx": 212}, {"w": "yXYYxY", "n": 1, "status": "trivial", "ms_idx": 56}, {"w": "yXYYxY", "n": 2, "status": "trivial", "ms_idx": 224}, {"w": "yXYYxY", "n": 3, "status": "trivial", "ms_idx": 347}, {"w": "yXYYxY", "n": 4, "status": "trivial", "ms_idx": 433}, {"w": "yXYYxY", "n": 5, "status": "17_33", "ms_idx": 1032, "rep_idx": 85}, {"w": "yXYYxY", "n": 6, "status": "16_9", "ms_idx": 706, "rep_idx": 133}, {"w": "yXYYxY", "n": 7, "status": "23_23", "ms_idx": 824, "rep_idx": 190}, {"w": "yXYYxy", "n": 1, "status": "trivial", "ms_idx": 55}, {"w": "yXYYxy", "n": 2, "status": "trivial", "ms_idx": 223}, {"w": "yXYYxy", "n": 3, "status": "13_1", "ms_idx": 755, "rep_idx": 0}, {"w": "yXYYxy", "n": 4, "status": "trivial", "ms_idx": 432}, {"w": "yXYYxy", "n": 5, "status": "17_32", "ms_idx": 1084, "rep_idx": 84}, {"w": "yXYYxy", "n": 6, "status": "16_8", "ms_idx": 901, "rep_idx": 132}, {"w": "yXYYxy", "n": 7, "status": "21_38", "ms_idx": 1068, "rep_idx": 189}, {"w": "yxYYXY", "n": 1, "status": "trivial", "ms_idx": 40}, {"w": "yxYYXY", "n": 2, "status": "trivial", "ms_idx": 208}, {"w": "yxYYXY", "n": 3, "status": "trivial", "ms_idx": 336}, {"w": "yxYYXY", "n": 4, "status": "14_1", "ms_idx": 738, "rep_idx": 5}, {"w": "yxYYXY", "n": 5, "status": "trivial", "ms_idx": 568}, {"w": "yxYYXY", "n": 6, "status": "19_33", "ms_idx": 1122, "rep_idx": 126}, {"w": "yxYYXY", "n": 7, "status": "17_41", "ms_idx": 1164, "rep_idx": 198}, {"w": "yxYYXy", "n": 1, "status": "trivial", "ms_idx": 39}, {"w": "yxYYXy", "n": 2, "status": "trivial", "ms_idx": 207}, {"w": "yxYYXy", "n": 3, "status": "trivial", "ms_idx": 335}, {"w": "yxYYXy", "n": 4, "status": "14_1", "ms_idx": 722, "rep_idx": 5}, {"w": "yxYYXy", "n": 5, "status": "trivial", "ms_idx": 567}, {"w": "yxYYXy", "n": 6, "status": "19_33", "ms_idx": 985, "rep_idx": 126}, {"w": "yxYYXy", "n": 7, "status": "19_37", "ms_idx": 734, "rep_idx": 183}, {"w": "yxyyXY", "n": 1, "status": "trivial", "ms_idx": 34}, {"w": "yxyyXY", "n": 2, "status": "trivial", "ms_idx": 202}, {"w": "yxyyXY", "n": 3, "status": "trivial", "ms_idx": 332}, {"w": "yxyyXY", "n": 4, "status": "15_10", "ms_idx": 673, "rep_idx": 45}, {"w": "yxyyXY", "n": 5, "status": "14_1", "ms_idx": 1181, "rep_idx": 5}, {"w": "yxyyXY", "n": 6, "status": "17_34", "ms_idx": 645, "rep_idx": 125}, {"w": "yxyyXY", "n": 7, "status": "15_12", "ms_idx": 1041, "rep_idx": 195}, {"w": "yxyyXy", "n": 1, "status": "trivial", "ms_idx": 33}, {"w": "yxyyXy", "n": 2, "status": "trivial", "ms_idx": 201}, {"w": "yxyyXy", "n": 3, "status": "trivial", "ms_idx": 331}, {"w": "yxyyXy", "n": 4, "status": "15_10", "ms_idx": 836, "rep_idx": 45}, {"w": "yxyyXy", "n": 5, "status": "14_1", "ms_idx": 1138, "rep_idx": 5}, {"w": "yxyyXy", "n": 6, "status": "17_34", "ms_idx": 1102, "rep_idx": 125}, {"w": "yxyyXy", "n": 7, "status": "21_34", "ms_idx": 1006, "rep_idx": 181}, {"w": "YxYXYY", "n": 1, "status": "trivial", "ms_idx": 67}, {"w": "YxYXYY", "n": 2, "status": "trivial", "ms_idx": 233}, {"w": "YxYXYY", "n": 3, "status": "13_1", "ms_idx": 1166, "rep_idx": 0}, {"w": "YxYXYY", "n": 4, "status": "15_1", "ms_idx": 795, "rep_idx": 1}, {"w": "YxYXYY", "n": 5, "status": "16_1", "ms_idx": 727, "rep_idx": 2}, {"w": "YxYXYY", "n": 6, "status": "17_1", "ms_idx": 916, "rep_idx": 3}, {"w": "YxYXYY", "n": 7, "status": "18_7", "ms_idx": 995, "rep_idx": 197}, {"w": "YxyXYY", "n": 1, "status": "trivial", "ms_idx": 66}, {"w": "YxyXYY", "n": 2, "status": "trivial", "ms_idx": 232}, {"w": "YxyXYY", "n": 3, "status": "trivial", "ms_idx": 354}, {"w": "YxyXYY", "n": 4, "status": "trivial", "ms_idx": 541}, {"w": "YxyXYY", "n": 5, "status": "trivial", "ms_idx": 572}, {"w": "YxyXYY", "n": 6, "status": "trivial", "ms_idx": 603}, {"w": "YxyXYY", "n": 7, "status": "trivial", "ms_idx": 625}, {"w": "yXYxYY", "n": 1, "status": "trivial", "ms_idx": 54}, {"w": "yXYxYY", "n": 2, "status": "trivial", "ms_idx": 222}, {"w": "yXYxYY", "n": 3, "status": "trivial", "ms_idx": 346}, {"w": "yXYxYY", "n": 4, "status": "15_11", "ms_idx": 862, "rep_idx": 46}, {"w": "yXYxYY", "n": 5, "status": "14_1", "ms_idx": 740, "rep_idx": 5}, {"w": "yXYxYY", "n": 6, "status": "17_36", "ms_idx": 921, "rep_idx": 131}, {"w": "yXYxYY", "n": 7, "status": "15_13", "ms_idx": 1117, "rep_idx": 204}, {"w": "yXYxyy", "n": 1, "status": "trivial", "ms_idx": 53}, {"w": "yXYxyy", "n": 2, "status": "trivial", "ms_idx": 221}, {"w": "yXYxyy", "n": 3, "status": "trivial", "ms_idx": 345}, {"w": "yXYxyy", "n": 4, "status": "14_1", "ms_idx": 757, "rep_idx": 5}, {"w": "yXYxyy", "n": 5, "status": "trivial", "ms_idx": 570}, {"w": "yXYxyy", "n": 6, "status": "19_34", "ms_idx": 634, "rep_idx": 130}, {"w": "yXYxyy", "n": 7, "status": "17_42", "ms_idx": 899, "rep_idx": 203}, {"w": "yxYXYY", "n": 1, "status": "trivial", "ms_idx": 38}, {"w": "yxYXYY", "n": 2, "status": "trivial", "ms_idx": 206}, {"w": "yxYXYY", "n": 3, "status": "trivial", "ms_idx": 334}, {"w": "yxYXYY", "n": 4, "status": "trivial", "ms_idx": 424}, {"w": "yxYXYY", "n": 5, "status": "trivial", "ms_idx": 566}, {"w": "yxYXYY", "n": 6, "status": "trivial", "ms_idx": 597}, {"w": "yxYXYY", "n": 7, "status": "trivial", "ms_idx": 623}, {"w": "yxYXyy", "n": 1, "status": "trivial", "ms_idx": 37}, {"w": "yxYXyy", "n": 2, "status": "trivial", "ms_idx": 205}, {"w": "yxYXyy", "n": 3, "status": "trivial", "ms_idx": 333}, {"w": "yxYXyy", "n": 4, "status": "trivial", "ms_idx": 537}, {"w": "yxYXyy", "n": 5, "status": "trivial", "ms_idx": 565}, {"w": "yxYXyy", "n": 6, "status": "trivial", "ms_idx": 596}, {"w": "yxYXyy", "n": 7, "status": "trivial", "ms_idx": 622}, {"w": "yxyXYY", "n": 1, "status": "trivial", "ms_idx": 36}, {"w": "yxyXYY", "n": 2, "status": "trivial", "ms_idx": 204}, {"w": "yxyXYY", "n": 3, "status": "13_1", "ms_idx": 1103, "rep_idx": 0}, {"w": "yxyXYY", "n": 4, "status": "15_1", "ms_idx": 1163, "rep_idx": 1}, {"w": "yxyXYY", "n": 5, "status": "16_1", "ms_idx": 704, "rep_idx": 2}, {"w": "yxyXYY", "n": 6, "status": "17_1", "ms_idx": 1146, "rep_idx": 3}, {"w": "yxyXYY", "n": 7, "status": "18_7", "ms_idx": 796, "rep_idx": 197}, {"w": "yxyXyy", "n": 1, "status": "trivial", "ms_idx": 35}, {"w": "yxyXyy", "n": 2, "status": "trivial", "ms_idx": 203}, {"w": "yxyXyy", "n": 3, "status": "13_1", "ms_idx": 1063, "rep_idx": 0}, {"w": "yxyXyy", "n": 4, "status": "15_1", "ms_idx": 1019, "rep_idx": 1}, {"w": "yxyXyy", "n": 5, "status": "16_1", "ms_idx": 1128, "rep_idx": 2}, {"w": "yxyXyy", "n": 6, "status": "17_35", "ms_idx": 743, "rep_idx": 129}, {"w": "yxyXyy", "n": 7, "status": "18_6", "ms_idx": 982, "rep_idx": 196}, {"w": "yxxYXX", "n": 1, "status": "trivial", "ms_idx": 31}, {"w": "yxxYXX", "n": 2, "status": "14_2", "ms_idx": 700, "rep_idx": 6}, {"w": "yxxYXX", "n": 3, "status": "16_3", "ms_idx": 829, "rep_idx": 16}, {"w": "yxxYXX", "n": 4, "status": "18_2", "ms_idx": 765, "rep_idx": 48}, {"w": "yxxYXX", "n": 5, "status": "20_2", "ms_idx": 1080, "rep_idx": 87}, {"w": "yxxYXX", "n": 6, "status": "22_2", "ms_idx": 1185, "rep_idx": 135}, {"w": "yxxYXX", "n": 7, "status": "24_2", "ms_idx": 864, "rep_idx": 193}, {"w": "yxxyXX", "n": 1, "status": "trivial", "ms_idx": 30}, {"w": "yxxyXX", "n": 2, "status": "14_1", "ms_idx": 878, "rep_idx": 5}, {"w": "yxxyXX", "n": 3, "status": "16_2", "ms_idx": 774, "rep_idx": 15}, {"w": "yxxyXX", "n": 4, "status": "18_1", "ms_idx": 1066, "rep_idx": 47}, {"w": "yxxyXX", "n": 5, "status": "20_1", "ms_idx": 1061, "rep_idx": 86}, {"w": "yxxyXX", "n": 6, "status": "22_1", "ms_idx": 1106, "rep_idx": 134}, {"w": "yxxyXX", "n": 7, "status": "24_1", "ms_idx": 827, "rep_idx": 192}, {"w": "XYYYxY", "n": 1, "status": "trivial", "ms_idx": 64}, {"w": "XYYYxY", "n": 2, "status": "trivial", "ms_idx": 230}, {"w": "XYYYxY", "n": 3, "status": "trivial", "ms_idx": 352}, {"w": "XYYYxY", "n": 4, "status": "trivial", "ms_idx": 540}, {"w": "XYYYxY", "n": 5, "status": "17_31", "ms_idx": 1016, "rep_idx": 83}, {"w": "XYYYxY", "n": 6, "status": "trivial", "ms_idx": 602}, {"w": "XYYYxY", "n": 7, "status": "19_42", "ms_idx": 753, "rep_idx": 211}, {"w": "XYYYxy", "n": 1, "status": "trivial", "ms_idx": 63}, {"w": "XYYYxy", "n": 2, "status": "trivial", "ms_idx": 229}, {"w": "XYYYxy", "n": 3, "status": "trivial", "ms_idx": 351}, {"w": "XYYYxy", "n": 4, "status": "15_1", "ms_idx": 777, "rep_idx": 1}, {"w": "XYYYxy", "n": 5, "status": "17_30", "ms_idx": 699, "rep_idx": 82}, {"w": "XYYYxy", "n": 6, "status": "trivial", "ms_idx": 601}, {"w": "XYYYxy", "n": 7, "status": "18_11", "ms_idx": 667, "rep_idx": 210}, {"w": "XYYxYY", "n": 1, "status": "trivial", "ms_idx": 62}, {"w": "XYYxYY", "n": 2, "status": "trivial", "ms_idx": 228}, {"w": "XYYxYY", "n": 3, "status": "trivial", "ms_idx": 350}, {"w": "XYYxYY", "n": 4, "status": "trivial", "ms_idx": 435}, {"w": "XYYxYY", "n": 5, "status": "16_5", "ms_idx": 1012, "rep_idx": 90}, {"w": "XYYxYY", "n": 6, "status": "19_36", "ms_idx": 759, "rep_idx": 143}, {"w": "XYYxYY", "n": 7, "status": "20_11", "ms_idx": 872, "rep_idx": 209}, {"w": "XYYxyy", "n": 1, "status": "trivial", "ms_idx": 61}, {"w": "XYYxyy", "n": 2, "status": "trivial", "ms_idx": 227}, {"w": "XYYxyy", "n": 3, "status": "trivial", "ms_idx": 349}, {"w": "XYYxyy", "n": 4, "status": "trivial", "ms_idx": 434}, {"w": "XYYxyy", "n": 5, "status": "trivial", "ms_idx": 476}, {"w": "XYYxyy", "n": 6, "status": "trivial", "ms_idx": 505}, {"w": "XYYxyy", "n": 7, "status": "trivial", "ms_idx": 529}, {"w": "XYxYYY", "n": 1, "status": "trivial", "ms_idx": 60}, {"w": "XYxYYY", "n": 2, "status": "trivial", "ms_idx": 226}, {"w": "XYxYYY", "n": 3, "status": "trivial", "ms_idx": 348}, {"w": "XYxYYY", "n": 4, "status": "14_1", "ms_idx": 782, "rep_idx": 5}, {"w": "XYxYYY", "n": 5, "status": "trivial", "ms_idx": 475}, {"w": "XYxYYY", "n": 6, "status": "17_40", "ms_idx": 758, "rep_idx": 142}, {"w": "XYxYYY", "n": 7, "status": "19_41", "ms_idx": 870, "rep_idx": 208}, {"w": "XYxyyy", "n": 1, "status": "trivial", "ms_idx": 59}, {"w": "XYxyyy", "n": 2, "status": "trivial", "ms_idx": 225}, {"w": "XYxyyy", "n": 3, "status": "13_1", "ms_idx": 830, "rep_idx": 0}, {"w": "XYxyyy", "n": 4, "status": "15_11", "ms_idx": 766, "rep_idx": 46}, {"w": "XYxyyy", "n": 5, "status": "trivial", "ms_idx": 474}, {"w": "XYxyyy", "n": 6, "status": "17_39", "ms_idx": 1186, "rep_idx": 141}, {"w": "XYxyyy", "n": 7, "status": "18_10", "ms_idx": 865, "rep_idx": 207}, {"w": "XXYxxY", "n": 1, "status": "trivial", "ms_idx": 58}, {"w": "XXYxxY", "n": 2, "status": "14_1", "ms_idx": 802, "rep_idx": 5}, {"w": "XXYxxY", "n": 3, "status": "16_2", "ms_idx": 651, "rep_idx": 15}, {"w": "XXYxxY", "n": 4, "status": "18_3", "ms_idx": 909, "rep_idx": 49}, {"w": "XXYxxY", "n": 5, "status": "20_3", "ms_idx": 961, "rep_idx": 89}, {"w": "XXYxxY", "n": 6, "status": "22_4", "ms_idx": 929, "rep_idx": 140}, {"w": "XXYxxY", "n": 7, "status": "24_4", "ms_idx": 697, "rep_idx": 206}, {"w": "XXYxxy", "n": 1, "status": "trivial", "ms_idx": 57}, {"w": "XXYxxy", "n": 2, "status": "14_2", "ms_idx": 1059, "rep_idx": 6}, {"w": "XXYxxy", "n": 3, "status": "16_3", "ms_idx": 823, "rep_idx": 16}, {"w": "XXYxxy", "n": 4, "status": "18_2", "ms_idx": 988, "rep_idx": 48}, {"w": "XXYxxy", "n": 5, "status": "20_2", "ms_idx": 1098, "rep_idx": 87}, {"w": "XXYxxy", "n": 6, "status": "22_3", "ms_idx": 1081, "rep_idx": 139}, {"w": "XXYxxy", "n": 7, "status": "24_3", "ms_idx": 1118, "rep_idx": 205}, {"w": "YYYYYYY", "n": 1, "status": "trivial", "ms_idx": 169}, {"w": "YYYYYYY", "n": 2, "status": "trivial", "ms_idx": 307}, {"w": "YYYYYYY", "n": 3, "status": "trivial", "ms_idx": 405}, {"w": "YYYYYYY", "n": 4, "status": "trivial", "ms_idx": 457}, {"w": "YYYYYYY", "n": 5, "status": "trivial", "ms_idx": 492}, {"w": "YYYYYYY", "n": 6, "status": "trivial", "ms_idx": 516}, {"w": "YYYYYYY", "n": 7, "status": "trivial", "ms_idx": 532}, {"w": "yyyyyyy", "n": 1, "status": "trivial", "ms_idx": 120}, {"w": "yyyyyyy", "n": 2, "status": "trivial", "ms_idx": 272}, {"w": "yyyyyyy", "n": 3, "status": "trivial", "ms_idx": 381}, {"w": "yyyyyyy", "n": 4, "status": "trivial", "ms_idx": 447}, {"w": "yyyyyyy", "n": 5, "status": "trivial", "ms_idx": 484}, {"w": "yyyyyyy", "n": 6, "status": "trivial", "ms_idx": 511}, {"w": "yyyyyyy", "n": 7, "status": "trivial", "ms_idx": 531}, {"w": "yyyyxYX", "n": 1, "status": "trivial", "ms_idx": 119}, {"w": "yyyyxYX", "n": 2, "status": "trivial", "ms_idx": 271}, {"w": "yyyyxYX", "n": 3, "status": "trivial", "ms_idx": 380}, {"w": "yyyyxYX", "n": 4, "status": "trivial", "ms_idx": 446}, {"w": "yyyyxYX", "n": 5, "status": "16_1", "ms_idx": 812, "rep_idx": 2}, {"w": "yyyyxYX", "n": 6, "status": "16_9", "ms_idx": 1179, "rep_idx": 133}, {"w": "yyyyxYX", "n": 7, "status": "19_47", "ms_idx": 1039, "rep_idx": 236}, {"w": "yyyyxyX", "n": 1, "status": "trivial", "ms_idx": 118}, {"w": "yyyyxyX", "n": 2, "status": "trivial", "ms_idx": 270}, {"w": "yyyyxyX", "n": 3, "status": "13_1", "ms_idx": 1005, "rep_idx": 0}, {"w": "yyyyxyX", "n": 4, "status": "trivial", "ms_idx": 445}, {"w": "yyyyxyX", "n": 5, "status": "trivial", "ms_idx": 581}, {"w": "yyyyxyX", "n": 6, "status": "16_8", "ms_idx": 856, "rep_idx": 132}, {"w": "yyyyxyX", "n": 7, "status": "19_46", "ms_idx": 873, "rep_idx": 235}, {"w": "yyyxYYX", "n": 1, "status": "trivial", "ms_idx": 117}, {"w": "yyyxYYX", "n": 2, "status": "trivial", "ms_idx": 269}, {"w": "yyyxYYX", "n": 3, "status": "trivial", "ms_idx": 379}, {"w": "yyyxYYX", "n": 4, "status": "15_11", "ms_idx": 641, "rep_idx": 46}, {"w": "yyyxYYX", "n": 5, "status": "16_5", "ms_idx": 778, "rep_idx": 90}, {"w": "yyyxYYX", "n": 6, "status": "trivial", "ms_idx": 510}, {"w": "yyyxYYX", "n": 7, "status": "19_45", "ms_idx": 947, "rep_idx": 234}, {"w": "yyyxyyX", "n": 1, "status": "trivial", "ms_idx": 112}, {"w": "yyyxyyX", "n": 2, "status": "trivial", "ms_idx": 264}, {"w": "yyyxyyX", "n": 3, "status": "trivial", "ms_idx": 374}, {"w": "yyyxyyX", "n": 4, "status": "14_1", "ms_idx": 846, "rep_idx": 5}, {"w": "yyyxyyX", "n": 5, "status": "trivial", "ms_idx": 580}, {"w": "yyyxyyX", "n": 6, "status": "trivial", "ms_idx": 606}, {"w": "yyyxyyX", "n": 7, "status": "21_40", "ms_idx": 879, "rep_idx": 233}, {"w": "yyyXYxY", "n": 1, "status": "trivial", "ms_idx": 122}, {"w": "yyyXYxY", "n": 2, "status": "trivial", "ms_idx": 274}, {"w": "yyyXYxY", "n": 3, "status": "13_1", "ms_idx": 1182, "rep_idx": 0}, {"w": "yyyXYxY", "n": 4, "status": "15_1", "ms_idx": 1031, "rep_idx": 1}, {"w": "yyyXYxY", "n": 5, "status": "16_1", "ms_idx": 841, "rep_idx": 2}, {"w": "yyyXYxY", "n": 6, "status": "17_35", "ms_idx": 787, "rep_idx": 129}, {"w": "yyyXYxY", "n": 7, "status": "18_6", "ms_idx": 875, "rep_idx": 196}, {"w": "yyyXYxy", "n": 1, "status": "trivial", "ms_idx": 121}, {"w": "yyyXYxy", "n": 2, "status": "trivial", "ms_idx": 273}, {"w": "yyyXYxy", "n": 3, "status": "trivial", "ms_idx": 382}, {"w": "yyyXYxy", "n": 4, "status": "trivial", "ms_idx": 551}, {"w": "yyyXYxy", "n": 5, "status": "trivial", "ms_idx": 582}, {"w": "yyyXYxy", "n": 6, "status": "trivial", "ms_idx": 610}, {"w": "yyyXYxy", "n": 7, "status": "trivial", "ms_idx": 1046}, {"w": "yyyxYXY", "n": 1, "status": "trivial", "ms_idx": 116}, {"w": "yyyxYXY", "n": 2, "status": "trivial", "ms_idx": 268}, {"w": "yyyxYXY", "n": 3, "status": "trivial", "ms_idx": 378}, {"w": "yyyxYXY", "n": 4, "status": "15_1", "ms_idx": 770, "rep_idx": 1}, {"w": "yyyxYXY", "n": 5, "status": "17_33", "ms_idx": 1161, "rep_idx": 85}, {"w": "yyyxYXY", "n": 6, "status": "trivial", "ms_idx": 509}, {"w": "yyyxYXY", "n": 7, "status": "18_9", "ms_idx": 951, "rep_idx": 202}, {"w": "yyyxYXy", "n": 1, "status": "trivial", "ms_idx": 115}, {"w": "yyyxYXy", "n": 2, "status": "trivial", "ms_idx": 267}, {"w": "yyyxYXy", "n": 3, "status": "trivial", "ms_idx": 377}, {"w": "yyyxYXy", "n": 4, "status": "15_1", "ms_idx": 763, "rep_idx": 1}, {"w": "yyyxYXy", "n": 5, "status": "17_33", "ms_idx": 967, "rep_idx": 85}, {"w": "yyyxYXy", "n": 6, "status": "trivial", "ms_idx": 609}, {"w": "yyyxYXy", "n": 7, "status": "18_9", "ms_idx": 679, "rep_idx": 202}, {"w": "yyyxyXY", "n": 1, "status": "trivial", "ms_idx": 114}, {"w": "yyyxyXY", "n": 2, "status": "trivial", "ms_idx": 266}, {"w": "yyyxyXY", "n": 3, "status": "trivial", "ms_idx": 376}, {"w": "yyyxyXY", "n": 4, "status": "trivial", "ms_idx": 550}, {"w": "yyyxyXY", "n": 5, "status": "17_32", "ms_idx": 828, "rep_idx": 84}, {"w": "yyyxyXY", "n": 6, "status": "trivial", "ms_idx": 608}, {"w": "yyyxyXY", "n": 7, "status": "19_40", "ms_idx": 837, "rep_idx": 201}, {"w": "yyyxyXy", "n": 1, "status": "trivial", "ms_idx": 113}, {"w": "yyyxyXy", "n": 2, "status": "trivial", "ms_idx": 265}, {"w": "yyyxyXy", "n": 3, "status": "trivial", "ms_idx": 375}, {"w": "yyyxyXy", "n": 4, "status": "trivial", "ms_idx": 549}, {"w": "yyyxyXy", "n": 5, "status": "17_32", "ms_idx": 924, "rep_idx": 84}, {"w": "yyyxyXy", "n": 6, "status": "trivial", "ms_idx": 607}, {"w": "yyyxyXy", "n": 7, "status": "19_40", "ms_idx": 835, "rep_idx": 201}, {"w": "yyxYYYX", "n": 1, "status": "trivial", "ms_idx": 111}, {"w": "yyxYYYX", "n": 2, "status": "trivial", "ms_idx": 263}, {"w": "yyxYYYX", "n": 3, "status": "trivial", "ms_idx": 373}, {"w": "yyxYYYX", "n": 4, "status": "trivial", "ms_idx": 444}, {"w": "yyxYYYX", "n": 5, "status": "trivial", "ms_idx": 483}, {"w": "yyxYYYX", "n": 6, "status": "trivial", "ms_idx": 668}, {"w": "yyxYYYX", "n": 7, "status": "19_44", "ms_idx": 648, "rep_idx": 232}, {"w": "yyxyyyX", "n": 1, "status": "trivial", "ms_idx": 102}, {"w": "yyxyyyX", "n": 2, "status": "trivial", "ms_idx": 254}, {"w": "yyxyyyX", "n": 3, "status": "13_1", "ms_idx": 735, "rep_idx": 0}, {"w": "yyxyyyX", "n": 4, "status": "trivial", "ms_idx": 438}, {"w": "yyxyyyX", "n": 5, "status": "trivial", "ms_idx": 579}, {"w": "yyxyyyX", "n": 6, "status": "18_4", "ms_idx": 1124, "rep_idx": 160}, {"w": "yyxyyyX", "n": 7, "status": "21_39", "ms_idx": 800, "rep_idx": 230}, {"w": "yyXYYxY", "n": 1, "status": "trivial", "ms_idx": 126}, {"w": "yyXYYxY", "n": 2, "status": "trivial", "ms_idx": 278}, {"w": "yyXYYxY", "n": 3, "status": "trivial", "ms_idx": 385}, {"w": "yyXYYxY", "n": 4, "status": "trivial", "ms_idx": 449}, {"w": "yyXYYxY", "n": 5, "status": "17_33", "ms_idx": 1105, "rep_idx": 85}, {"w": "yyXYYxY", "n": 6, "status": "16_9", "ms_idx": 989, "rep_idx": 133}, {"w": "yyXYYxY", "n": 7, "status": "19_48", "ms_idx": 866, "rep_idx": 238}, {"w": "yyXYYxy", "n": 1, "status": "trivial", "ms_idx": 125}, {"w": "yyXYYxy", "n": 2, "status": "trivial", "ms_idx": 277}, {"w": "yyXYYxy", "n": 3, "status": "13_1", "ms_idx": 1143, "rep_idx": 0}, {"w": "yyXYYxy", "n": 4, "status": "trivial", "ms_idx": 448}, {"w": "yyXYYxy", "n": 5, "status": "17_32", "ms_idx": 897, "rep_idx": 84}, {"w": "yyXYYxy", "n": 6, "status": "16_8", "ms_idx": 781, "rep_idx": 132}, {"w": "yyXYYxy", "n": 7, "status": "21_38", "ms_idx": 1085, "rep_idx": 189}, {"w": "yyxYYXY", "n": 1, "status": "trivial", "ms_idx": 110}, {"w": "yyxYYXY", "n": 2, "status": "trivial", "ms_idx": 262}, {"w": "yyxYYXY", "n": 3, "status": "trivial", "ms_idx": 372}, {"w": "yyxYYXY", "n": 4, "status": "trivial", "ms_idx": 443}, {"w": "yyxYYXY", "n": 5, "status": "trivial", "ms_idx": 482}, {"w": "yyxYYXY", "n": 6, "status": "trivial", "ms_idx": 508}, {"w": "yyxYYXY", "n": 7, "status": "trivial", "ms_idx": 629}, {"w": "yyxYYXy", "n": 1, "status": "trivial", "ms_idx": 109}, {"w": "yyxYYXy", "n": 2, "status": "trivial", "ms_idx": 261}, {"w": "yyxYYXy", "n": 3, "status": "trivial", "ms_idx": 371}, {"w": "yyxYYXy", "n": 4, "status": "trivial", "ms_idx": 442}, {"w": "yyxYYXy", "n": 5, "status": "trivial", "ms_idx": 481}, {"w": "yyxYYXy", "n": 6, "status": "trivial", "ms_idx": 507}, {"w": "yyxYYXy", "n": 7, "status": "trivial", "ms_idx": 628}, {"w": "yyxyyXY", "n": 1, "status": "trivial", "ms_idx": 104}, {"w": "yyxyyXY", "n": 2, "status": "trivial", "ms_idx": 256}, {"w": "yyxyyXY", "n": 3, "status": "trivial", "ms_idx": 368}, {"w": "yyxyyXY", "n": 4, "status": "trivial", "ms_idx": 439}, {"w": "yyxyyXY", "n": 5, "status": "16_4", "ms_idx": 1125, "rep_idx": 88}, {"w": "yyxyyXY", "n": 6, "status": "19_35", "ms_idx": 671, "rep_idx": 138}, {"w": "yyxyyXY", "n": 7, "status": "20_10", "ms_idx": 1110, "rep_idx": 200}, {"w": "yyxyyXy", "n": 1, "status": "trivial", "ms_idx": 103}, {"w": "yyxyyXy", "n": 2, "status": "trivial", "ms_idx": 255}, {"w": "yyxyyXy", "n": 3, "status": "trivial", "ms_idx": 367}, {"w": "yyxyyXy", "n": 4, "status": "trivial", "ms_idx": 546}, {"w": "yyxyyXy", "n": 5, "status": "16_4", "ms_idx": 965, "rep_idx": 88}, {"w": "yyxyyXy", "n": 6, "status": "19_35", "ms_idx": 658, "rep_idx": 138}, {"w": "yyxyyXy", "n": 7, "status": "20_10", "ms_idx": 709, "rep_idx": 200}, {"w": "YYxYXYY", "n": 1, "status": "trivial", "ms_idx": 168}, {"w": "YYxYXYY", "n": 2, "status": "trivial", "ms_idx": 306}, {"w": "YYxYXYY", "n": 3, "status": "trivial", "ms_idx": 404}, {"w": "YYxYXYY", "n": 4, "status": "trivial", "ms_idx": 558}, {"w": "YYxYXYY", "n": 5, "status": "17_33", "ms_idx": 1004, "rep_idx": 85}, {"w": "YYxYXYY", "n": 6, "status": "16_9", "ms_idx": 776, "rep_idx": 133}, {"w": "YYxYXYY", "n": 7, "status": "23_23", "ms_idx": 1072, "rep_idx": 190}, {"w": "YYxyXYY", "n": 1, "status": "trivial", "ms_idx": 167}, {"w": "YYxyXYY", "n": 2, "status": "trivial", "ms_idx": 305}, {"w": "YYxyXYY", "n": 3, "status": "13_1", "ms_idx": 1189, "rep_idx": 0}, {"w": "YYxyXYY", "n": 4, "status": "trivial", "ms_idx": 557}, {"w": "YYxyXYY", "n": 5, "status": "17_32", "ms_idx": 868, "rep_idx": 84}, {"w": "YYxyXYY", "n": 6, "status": "16_8", "ms_idx": 892, "rep_idx": 132}, {"w": "YYxyXYY", "n": 7, "status": "21_38", "ms_idx": 1133, "rep_idx": 189}, {"w": "yyXYxYY", "n": 1, "status": "trivial", "ms_idx": 124}, {"w": "yyXYxYY", "n": 2, "status": "trivial", "ms_idx": 276}, {"w": "yyXYxYY", "n": 3, "status": "trivial", "ms_idx": 384}, {"w": "yyXYxYY", "n": 4, "status": "15_11", "ms_idx": 1037, "rep_idx": 46}, {"w": "yyXYxYY", "n": 5, "status": "14_1", "ms_idx": 1177, "rep_idx": 5}, {"w": "yyXYxYY", "n": 6, "status": "17_36", "ms_idx": 729, "rep_idx": 131}, {"w": "yyXYxYY", "n": 7, "status": "15_15", "ms_idx": 885, "rep_idx": 237}, {"w": "yyXYxyy", "n": 1, "status": "trivial", "ms_idx": 123}, {"w": "yyXYxyy", "n": 2, "status": "trivial", "ms_idx": 275}, {"w": "yyXYxyy", "n": 3, "status": "trivial", "ms_idx": 383}, {"w": "yyXYxyy", "n": 4, "status": "14_1", "ms_idx": 973, "rep_idx": 5}, {"w": "yyXYxyy", "n": 5, "status": "trivial", "ms_idx": 583}, {"w": "yyXYxyy", "n": 6, "status": "19_34", "ms_idx": 1137, "rep_idx": 130}, {"w": "yyXYxyy", "n": 7, "status": "17_42", "ms_idx": 1101, "rep_idx": 203}, {"w": "yyxYXYY", "n": 1, "status": "trivial", "ms_idx": 108}, {"w": "yyxYXYY", "n": 2, "status": "trivial", "ms_idx": 260}, {"w": "yyxYXYY", "n": 3, "status": "13_1", "ms_idx": 1170, "rep_idx": 0}, {"w": "yyxYXYY", "n": 4, "status": "trivial", "ms_idx": 441}, {"w": "yyxYXYY", "n": 5, "status": "17_31", "ms_idx": 833, "rep_idx": 83}, {"w": "yyxYXYY", "n": 6, "status": "16_7", "ms_idx": 1092, "rep_idx": 128}, {"w": "yyxYXYY", "n": 7, "status": "21_35", "ms_idx": 745, "rep_idx": 185}, {"w": "yyxYXyy", "n": 1, "status": "trivial", "ms_idx": 107}, {"w": "yyxYXyy", "n": 2, "status": "trivial", "ms_idx": 259}, {"w": "yyxYXyy", "n": 3, "status": "13_1", "ms_idx": 867, "rep_idx": 0}, {"w": "yyxYXyy", "n": 4, "status": "trivial", "ms_idx": 548}, {"w": "yyxYXyy", "n": 5, "status": "17_31", "ms_idx": 962, "rep_idx": 83}, {"w": "yyxYXyy", "n": 6, "status": "16_7", "ms_idx": 731, "rep_idx": 128}, {"w": "yyxYXyy", "n": 7, "status": "21_35", "ms_idx": 708, "rep_idx": 185}, {"w": "yyxyXYY", "n": 1, "status": "trivial", "ms_idx": 106}, {"w": "yyxyXYY", "n": 2, "status": "trivial", "ms_idx": 258}, {"w": "yyxyXYY", "n": 3, "status": "trivial", "ms_idx": 370}, {"w": "yyxyXYY", "n": 4, "status": "trivial", "ms_idx": 440}, {"w": "yyxyXYY", "n": 5, "status": "17_30", "ms_idx": 747, "rep_idx": 82}, {"w": "yyxyXYY", "n": 6, "status": "16_6", "ms_idx": 1055, "rep_idx": 127}, {"w": "yyxyXYY", "n": 7, "status": "19_43", "ms_idx": 839, "rep_idx": 231}, {"w": "yyxyXyy", "n": 1, "status": "trivial", "ms_idx": 105}, {"w": "yyxyXyy", "n": 2, "status": "trivial", "ms_idx": 257}, {"w": "yyxyXyy", "n": 3, "status": "trivial", "ms_idx": 369}, {"w": "yyxyXyy", "n": 4, "status": "trivial", "ms_idx": 547}, {"w": "yyxyXyy", "n": 5, "status": "17_30", "ms_idx": 696, "rep_idx": 82}, {"w": "yyxyXyy", "n": 6, "status": "16_10", "ms_idx": 855, "rep_idx": 161}, {"w": "yyxyXyy", "n": 7, "status": "23_22", "ms_idx": 637, "rep_idx": 184}, {"w": "yyxxYXX", "n": 1, "status": "trivial", "ms_idx": 101}, {"w": "yyxxYXX", "n": 2, "status": "trivial", "ms_idx": 253}, {"w": "yyxxYXX", "n": 3, "status": "17_17", "ms_idx": 794, "rep_idx": 32}, {"w": "yyxxYXX", "n": 4, "status": "19_16", "ms_idx": 644, "rep_idx": 65}, {"w": "yyxxYXX", "n": 5, "status": "21_15", "ms_idx": 1091, "rep_idx": 106}, {"w": "yyxxYXX", "n": 6, "status": "23_10", "ms_idx": 850, "rep_idx": 159}, {"w": "yyxxYXX", "n": 7, "status": "25_16", "ms_idx": 1135, "rep_idx": 229}, {"w": "yyxxyXX", "n": 1, "status": "trivial", "ms_idx": 100}, {"w": "yyxxyXX", "n": 2, "status": "trivial", "ms_idx": 252}, {"w": "yyxxyXX", "n": 3, "status": "17_16", "ms_idx": 815, "rep_idx": 31}, {"w": "yyxxyXX", "n": 4, "status": "19_15", "ms_idx": 1142, "rep_idx": 64}, {"w": "yyxxyXX", "n": 5, "status": "21_14", "ms_idx": 798, "rep_idx": 105}, {"w": "yyxxyXX", "n": 6, "status": "23_9", "ms_idx": 691, "rep_idx": 158}, {"w": "yyxxyXX", "n": 7, "status": "25_15", "ms_idx": 1042, "rep_idx": 228}, {"w": "yxYYYYX", "n": 1, "status": "trivial", "ms_idx": 99}, {"w": "yxYYYYX", "n": 2, "status": "trivial", "ms_idx": 251}, {"w": "yxYYYYX", "n": 3, "status": "trivial", "ms_idx": 366}, {"w": "yxYYYYX", "n": 4, "status": "15_1", "ms_idx": 854, "rep_idx": 1}, {"w": "yxYYYYX", "n": 5, "status": "14_1", "ms_idx": 838, "rep_idx": 5}, {"w": "yxYYYYX", "n": 6, "status": "17_37", "ms_idx": 686, "rep_idx": 136}, {"w": "yxYYYYX", "n": 7, "status": "trivial", "ms_idx": 627}, {"w": "yxyyyyX", "n": 1, "status": "trivial", "ms_idx": 84}, {"w": "yxyyyyX", "n": 2, "status": "trivial", "ms_idx": 238}, {"w": "yxyyyyX", "n": 3, "status": "trivial", "ms_idx": 358}, {"w": "yxyyyyX", "n": 4, "status": "trivial", "ms_idx": 543}, {"w": "yxyyyyX", "n": 5, "status": "trivial", "ms_idx": 573}, {"w": "yxyyyyX", "n": 6, "status": "17_38", "ms_idx": 1130, "rep_idx": 137}, {"w": "yxyyyyX", "n": 7, "status": "trivial", "ms_idx": 626}, {"w": "YXYYYxY", "n": 1, "status": "trivial", "ms_idx": 166}, {"w": "YXYYYxY", "n": 2, "status": "trivial", "ms_idx": 304}, {"w": "YXYYYxY", "n": 3, "status": "trivial", "ms_idx": 403}, {"w": "YXYYYxY", "n": 4, "status": "trivial", "ms_idx": 556}, {"w": "YXYYYxY", "n": 5, "status": "17_31", "ms_idx": 1069, "rep_idx": 83}, {"w": "YXYYYxY", "n": 6, "status": "trivial", "ms_idx": 615}, {"w": "YXYYYxY", "n": 7, "status": "19_42", "ms_idx": 953, "rep_idx": 211}, {"w": "YXYYYxy", "n": 1, "status": "trivial", "ms_idx": 165}, {"w": "YXYYYxy", "n": 2, "status": "trivial", "ms_idx": 303}, {"w": "YXYYYxy", "n": 3, "status": "trivial", "ms_idx": 402}, {"w": "YXYYYxy", "n": 4, "status": "15_1", "ms_idx": 881, "rep_idx": 1}, {"w": "YXYYYxy", "n": 5, "status": "17_30", "ms_idx": 1044, "rep_idx": 82}, {"w": "YXYYYxy", "n": 6, "status": "trivial", "ms_idx": 614}, {"w": "YXYYYxy", "n": 7, "status": "18_11", "ms_idx": 762, "rep_idx": 210}, {"w": "YxYYYXY", "n": 1, "status": "trivial", "ms_idx": 162}, {"w": "YxYYYXY", "n": 2, "status": "trivial", "ms_idx": 300}, {"w": "YxYYYXY", "n": 3, "status": "trivial", "ms_idx": 534}, {"w": "YxYYYXY", "n": 4, "status": "14_1", "ms_idx": 1115, "rep_idx": 5}, {"w": "YxYYYXY", "n": 5, "status": "trivial", "ms_idx": 589}, {"w": "YxYYYXY", "n": 6, "status": "17_40", "ms_idx": 666, "rep_idx": 142}, {"w": "YxYYYXY", "n": 7, "status": "19_41", "ms_idx": 923, "rep_idx": 208}, {"w": "YxyyyXY", "n": 1, "status": "trivial", "ms_idx": 157}, {"w": "YxyyyXY", "n": 2, "status": "trivial", "ms_idx": 295}, {"w": "YxyyyXY", "n": 3, "status": "13_1", "ms_idx": 1174, "rep_idx": 0}, {"w": "YxyyyXY", "n": 4, "status": "15_11", "ms_idx": 1113, "rep_idx": 46}, {"w": "YxyyyXY", "n": 5, "status": "trivial", "ms_idx": 490}, {"w": "YxyyyXY", "n": 6, "status": "17_39", "ms_idx": 793, "rep_idx": 141}, {"w": "YxyyyXY", "n": 7, "status": "18_10", "ms_idx": 636, "rep_idx": 207}, {"w": "yXYYYxY", "n": 1, "status": "trivial", "ms_idx": 136}, {"w": "yXYYYxY", "n": 2, "status": "trivial", "ms_idx": 284}, {"w": "yXYYYxY", "n": 3, "status": "trivial", "ms_idx": 390}, {"w": "yXYYYxY", "n": 4, "status": "trivial", "ms_idx": 552}, {"w": "yXYYYxY", "n": 5, "status": "17_31", "ms_idx": 871, "rep_idx": 83}, {"w": "yXYYYxY", "n": 6, "status": "trivial", "ms_idx": 611}, {"w": "yXYYYxY", "n": 7, "status": "19_42", "ms_idx": 752, "rep_idx": 211}, {"w": "yXYYYxy", "n": 1, "status": "trivial", "ms_idx": 135}, {"w": "yXYYYxy", "n": 2, "status": "trivial", "ms_idx": 283}, {"w": "yXYYYxy", "n": 3, "status": "trivial", "ms_idx": 389}, {"w": "yXYYYxy", "n": 4, "status": "15_1", "ms_idx": 1167, "rep_idx": 1}, {"w": "yXYYYxy", "n": 5, "status": "17_30", "ms_idx": 1035, "rep_idx": 82}, {"w": "yXYYYxy", "n": 6, "status": "trivial", "ms_idx": 513}, {"w": "yXYYYxy", "n": 7, "status": "18_11", "ms_idx": 772, "rep_idx": 210}, {"w": "yxYYYXY", "n": 1, "status": "trivial", "ms_idx": 98}, {"w": "yxYYYXY", "n": 2, "status": "trivial", "ms_idx": 250}, {"w": "yxYYYXY", "n": 3, "status": "13_1", "ms_idx": 1119, "rep_idx": 0}, {"w": "yxYYYXY", "n": 4, "status": "15_10", "ms_idx": 853, "rep_idx": 45}, {"w": "yxYYYXY", "n": 5, "status": "trivial", "ms_idx": 480}, {"w": "yxYYYXY", "n": 6, "status": "17_38", "ms_idx": 684, "rep_idx": 137}, {"w": "yxYYYXY", "n": 7, "status": "18_8", "ms_idx": 993, "rep_idx": 199}, {"w": "yxYYYXy", "n": 1, "status": "trivial", "ms_idx": 97}, {"w": "yxYYYXy", "n": 2, "status": "trivial", "ms_idx": 249}, {"w": "yxYYYXy", "n": 3, "status": "13_1", "ms_idx": 769, "rep_idx": 0}, {"w": "yxYYYXy", "n": 4, "status": "15_10", "ms_idx": 1015, "rep_idx": 45}, {"w": "yxYYYXy", "n": 5, "status": "trivial", "ms_idx": 479}, {"w": "yxYYYXy", "n": 6, "status": "17_38", "ms_idx": 968, "rep_idx": 137}, {"w": "yxYYYXy", "n": 7, "status": "18_8", "ms_idx": 1108, "rep_idx": 199}, {"w": "yxyyyXY", "n": 1, "status": "trivial", "ms_idx": 86}, {"w": "yxyyyXY", "n": 2, "status": "trivial", "ms_idx": 240}, {"w": "yxyyyXY", "n": 3, "status": "trivial", "ms_idx": 359}, {"w": "yxyyyXY", "n": 4, "status": "14_1", "ms_idx": 1083, "rep_idx": 5}, {"w": "yxyyyXY", "n": 5, "status": "trivial", "ms_idx": 478}, {"w": "yxyyyXY", "n": 6, "status": "17_37", "ms_idx": 670, "rep_idx": 136}, {"w": "yxyyyXY", "n": 7, "status": "19_39", "ms_idx": 1111, "rep_idx": 194}, {"w": "yxyyyXy", "n": 1, "status": "trivial", "ms_idx": 85}, {"w": "yxyyyXy", "n": 2, "status": "trivial", "ms_idx": 239}, {"w": "yxyyyXy", "n": 3, "status": "trivial", "ms_idx": 533}, {"w": "yxyyyXy", "n": 4, "status": "14_1", "ms_idx": 1049, "rep_idx": 5}, {"w": "yxyyyXy", "n": 5, "status": "trivial", "ms_idx": 574}, {"w": "yxyyyXy", "n": 6, "status": "17_37", "ms_idx": 657, "rep_idx": 136}, {"w": "yxyyyXy", "n": 7, "status": "19_39", "ms_idx": 710, "rep_idx": 194}, {"w": "YXYYxYY", "n": 1, "status": "trivial", "ms_idx": 164}, {"w": "YXYYxYY", "n": 2, "status": "trivial", "ms_idx": 302}, {"w": "YXYYxYY", "n": 3, "status": "trivial", "ms_idx": 401}, {"w": "YXYYxYY", "n": 4, "status": "trivial", "ms_idx": 555}, {"w": "YXYYxYY", "n": 5, "status": "16_5", "ms_idx": 858, "rep_idx": 90}, {"w": "YXYYxYY", "n": 6, "status": "19_36", "ms_idx": 665, "rep_idx": 143}, {"w": "YXYYxYY", "n": 7, "status": "20_11", "ms_idx": 925, "rep_idx": 209}, {"w": "YXYYxyy", "n": 1, "status": "trivial", "ms_idx": 163}, {"w": "YXYYxyy", "n": 2, "status": "trivial", "ms_idx": 301}, {"w": "YXYYxyy", "n": 3, "status": "trivial", "ms_idx": 400}, {"w": "YXYYxyy", "n": 4, "status": "trivial", "ms_idx": 456}, {"w": "YXYYxyy", "n": 5, "status": "trivial", "ms_idx": 491}, {"w": "YXYYxyy", "n": 6, "status": "trivial", "ms_idx": 515}, {"w": "YXYYxyy", "n": 7, "status": "trivial", "ms_idx": 633}, {"w": "YxYYXYY", "n": 1, "status": "trivial", "ms_idx": 161}, {"w": "YxYYXYY", "n": 2, "status": "trivial", "ms_idx": 299}, {"w": "YxYYXYY", "n": 3, "status": "trivial", "ms_idx": 399}, {"w": "YxYYXYY", "n": 4, "status": "15_11", "ms_idx": 1116, "rep_idx": 46}, {"w": "YxYYXYY", "n": 5, "status": "14_1", "ms_idx": 857, "rep_idx": 5}, {"w": "YxYYXYY", "n": 6, "status": "17_36", "ms_idx": 932, "rep_idx": 131}, {"w": "YxYYXYY", "n": 7, "status": "21_37", "ms_idx": 922, "rep_idx": 188}, {"w": "YxyyXYY", "n": 1, "status": "trivial", "ms_idx": 158}, {"w": "YxyyXYY", "n": 2, "status": "trivial", "ms_idx": 296}, {"w": "YxyyXYY", "n": 3, "status": "trivial", "ms_idx": 397}, {"w": "YxyyXYY", "n": 4, "status": "14_1", "ms_idx": 1030, "rep_idx": 5}, {"w": "YxyyXYY", "n": 5, "status": "trivial", "ms_idx": 587}, {"w": "YxyyXYY", "n": 6, "status": "19_34", "ms_idx": 1014, "rep_idx": 130}, {"w": "YxyyXYY", "n": 7, "status": "20_12", "ms_idx": 1058, "rep_idx": 212}, {"w": "yXYYxYY", "n": 1, "status": "trivial", "ms_idx": 134}, {"w": "yXYYxYY", "n": 2, "status": "trivial", "ms_idx": 282}, {"w": "yXYYxYY", "n": 3, "status": "trivial", "ms_idx": 388}, {"w": "yXYYxYY", "n": 4, "status": "trivial", "ms_idx": 451}, {"w": "yXYYxYY", "n": 5, "status": "16_5", "ms_idx": 1033, "rep_idx": 90}, {"w": "yXYYxYY", "n": 6, "status": "19_36", "ms_idx": 994, "rep_idx": 143}, {"w": "yXYYxYY", "n": 7, "status": "20_11", "ms_idx": 732, "rep_idx": 209}, {"w": "yXYYxyy", "n": 1, "status": "trivial", "ms_idx": 133}, {"w": "yXYYxyy", "n": 2, "status": "trivial", "ms_idx": 281}, {"w": "yXYYxyy", "n": 3, "status": "trivial", "ms_idx": 387}, {"w": "yXYYxyy", "n": 4, "status": "trivial", "ms_idx": 450}, {"w": "yXYYxyy", "n": 5, "status": "trivial", "ms_idx": 487}, {"w": "yXYYxyy", "n": 6, "status": "trivial", "ms_idx": 512}, {"w": "yXYYxyy", "n": 7, "status": "trivial", "ms_idx": 630}, {"w": "yxYYXYY", "n": 1, "status": "trivial", "ms_idx": 96}, {"w": "yxYYXYY", "n": 2, "status": "trivial", "ms_idx": 248}, {"w": "yxYYXYY", "n": 3, "status": "trivial", "ms_idx": 365}, {"w": "yxYYXYY", "n": 4, "status": "14_1", "ms_idx": 852, "rep_idx": 5}, {"w": "yxYYXYY", "n": 5, "status": "trivial", "ms_idx": 578}, {"w": "yxYYXYY", "n": 6, "status": "19_33", "ms_idx": 685, "rep_idx": 126}, {"w": "yxYYXYY", "n": 7, "status": "17_41", "ms_idx": 992, "rep_idx": 198}, {"w": "yxYYXyy", "n": 1, "status": "trivial", "ms_idx": 95}, {"w": "yxYYXyy", "n": 2, "status": "trivial", "ms_idx": 247}, {"w": "yxYYXyy", "n": 3, "status": "trivial", "ms_idx": 364}, {"w": "yxYYXyy", "n": 4, "status": "14_1", "ms_idx": 1175, "rep_idx": 5}, {"w": "yxYYXyy", "n": 5, "status": "trivial", "ms_idx": 577}, {"w": "yxYYXyy", "n": 6, "status": "19_33", "ms_idx": 869, "rep_idx": 126}, {"w": "yxYYXyy", "n": 7, "status": "19_37", "ms_idx": 834, "rep_idx": 183}, {"w": "yxyyXYY", "n": 1, "status": "trivial", "ms_idx": 88}, {"w": "yxyyXYY", "n": 2, "status": "trivial", "ms_idx": 242}, {"w": "yxyyXYY", "n": 3, "status": "trivial", "ms_idx": 361}, {"w": "yxyyXYY", "n": 4, "status": "15_10", "ms_idx": 816, "rep_idx": 45}, {"w": "yxyyXYY", "n": 5, "status": "14_1", "ms_idx": 1009, "rep_idx": 5}, {"w": "yxyyXYY", "n": 6, "status": "17_34", "ms_idx": 790, "rep_idx": 125}, {"w": "yxyyXYY", "n": 7, "status": "15_14", "ms_idx": 1001, "rep_idx": 225}, {"w": "yxyyXyy", "n": 1, "status": "trivial", "ms_idx": 87}, {"w": "yxyyXyy", "n": 2, "status": "trivial", "ms_idx": 241}, {"w": "yxyyXyy", "n": 3, "status": "trivial", "ms_idx": 360}, {"w": "yxyyXyy", "n": 4, "status": "15_10", "ms_idx": 1086, "rep_idx": 45}, {"w": "yxyyXyy", "n": 5, "status": "14_1", "ms_idx": 1062, "rep_idx": 5}, {"w": "yxyyXyy", "n": 6, "status": "17_34", "ms_idx": 1153, "rep_idx": 125}, {"w": "yxyyXyy", "n": 7, "status": "21_34", "ms_idx": 958, "rep_idx": 181}, {"w": "YxYXYYY", "n": 1, "status": "trivial", "ms_idx": 160}, {"w": "YxYXYYY", "n": 2, "status": "trivial", "ms_idx": 298}, {"w": "YxYXYYY", "n": 3, "status": "13_1", "ms_idx": 669, "rep_idx": 0}, {"w": "YxYXYYY", "n": 4, "status": "15_1", "ms_idx": 635, "rep_idx": 1}, {"w": "YxYXYYY", "n": 5, "status": "16_1", "ms_idx": 1003, "rep_idx": 2}, {"w": "YxYXYYY", "n": 6, "status": "17_1", "ms_idx": 775, "rep_idx": 3}, {"w": "YxYXYYY", "n": 7, "status": "18_7", "ms_idx": 1071, "rep_idx": 197}, {"w": "YxyXYYY", "n": 1, "status": "trivial", "ms_idx": 159}, {"w": "YxyXYYY", "n": 2, "status": "trivial", "ms_idx": 297}, {"w": "YxyXYYY", "n": 3, "status": "trivial", "ms_idx": 398}, {"w": "YxyXYYY", "n": 4, "status": "trivial", "ms_idx": 554}, {"w": "YxyXYYY", "n": 5, "status": "trivial", "ms_idx": 588}, {"w": "YxyXYYY", "n": 6, "status": "trivial", "ms_idx": 613}, {"w": "YxyXYYY", "n": 7, "status": "trivial", "ms_idx": 1132}, {"w": "yXYxYYY", "n": 1, "status": "trivial", "ms_idx": 132}, {"w": "yXYxYYY", "n": 2, "status": "trivial", "ms_idx": 280}, {"w": "yXYxYYY", "n": 3, "status": "trivial", "ms_idx": 386}, {"w": "yXYxYYY", "n": 4, "status": "14_1", "ms_idx": 656, "rep_idx": 5}, {"w": "yXYxYYY", "n": 5, "status": "trivial", "ms_idx": 486}, {"w": "yXYxYYY", "n": 6, "status": "17_40", "ms_idx": 945, "rep_idx": 142}, {"w": "yXYxYYY", "n": 7, "status": "19_41", "ms_idx": 693, "rep_idx": 208}, {"w": "yXYxyyy", "n": 1, "status": "trivial", "ms_idx": 131}, {"w": "yXYxyyy", "n": 2, "status": "trivial", "ms_idx": 279}, {"w": "yXYxyyy", "n": 3, "status": "13_1", "ms_idx": 847, "rep_idx": 0}, {"w": "yXYxyyy", "n": 4, "status": "15_11", "ms_idx": 820, "rep_idx": 46}, {"w": "yXYxyyy", "n": 5, "status": "trivial", "ms_idx": 485}, {"w": "yXYxyyy", "n": 6, "status": "17_39", "ms_idx": 822, "rep_idx": 141}, {"w": "yXYxyyy", "n": 7, "status": "18_10", "ms_idx": 1088, "rep_idx": 207}, {"w": "yxYXYYY", "n": 1, "status": "trivial", "ms_idx": 94}, {"w": "yxYXYYY", "n": 2, "status": "trivial", "ms_idx": 246}, {"w": "yxYXYYY", "n": 3, "status": "trivial", "ms_idx": 363}, {"w": "yxYXYYY", "n": 4, "status": "trivial", "ms_idx": 545}, {"w": "yxYXYYY", "n": 5, "status": "trivial", "ms_idx": 576}, {"w": "yxYXYYY", "n": 6, "status": "trivial", "ms_idx": 605}, {"w": "yxYXYYY", "n": 7, "status": "trivial", "ms_idx": 717}, {"w": "yxYXyyy", "n": 1, "status": "trivial", "ms_idx": 93}, {"w": "yxYXyyy", "n": 2, "status": "trivial", "ms_idx": 245}, {"w": "yxYXyyy", "n": 3, "status": "trivial", "ms_idx": 362}, {"w": "yxYXyyy", "n": 4, "status": "trivial", "ms_idx": 544}, {"w": "yxYXyyy", "n": 5, "status": "trivial", "ms_idx": 575}, {"w": "yxYXyyy", "n": 6, "status": "trivial", "ms_idx": 604}, {"w": "yxYXyyy", "n": 7, "status": "trivial", "ms_idx": 698}, {"w": "yxyXYYY", "n": 1, "status": "trivial", "ms_idx": 90}, {"w": "yxyXYYY", "n": 2, "status": "trivial", "ms_idx": 244}, {"w": "yxyXYYY", "n": 3, "status": "13_1", "ms_idx": 934, "rep_idx": 0}, {"w": "yxyXYYY", "n": 4, "status": "15_1", "ms_idx": 799, "rep_idx": 1}, {"w": "yxyXYYY", "n": 5, "status": "16_1", "ms_idx": 692, "rep_idx": 2}, {"w": "yxyXYYY", "n": 6, "status": "17_1", "ms_idx": 1162, "rep_idx": 3}, {"w": "yxyXYYY", "n": 7, "status": "18_7", "ms_idx": 721, "rep_idx": 197}, {"w": "yxyXyyy", "n": 1, "status": "trivial", "ms_idx": 89}, {"w": "yxyXyyy", "n": 2, "status": "trivial", "ms_idx": 243}, {"w": "yxyXyyy", "n": 3, "status": "13_1", "ms_idx": 1010, "rep_idx": 0}, {"w": "yxyXyyy", "n": 4, "status": "15_1", "ms_idx": 884, "rep_idx": 1}, {"w": "yxyXyyy", "n": 5, "status": "16_1", "ms_idx": 883, "rep_idx": 2}, {"w": "yxyXyyy", "n": 6, "status": "17_35", "ms_idx": 1107, "rep_idx": 129}, {"w": "yxyXyyy", "n": 7, "status": "18_6", "ms_idx": 998, "rep_idx": 196}, {"w": "yxYxYXX", "n": 1, "status": "trivial", "ms_idx": 92}, {"w": "yxYxYXX", "n": 2, "status": "15_9", "ms_idx": 703, "rep_idx": 14}, {"w": "yxYxYXX", "n": 3, "status": "17_15", "ms_idx": 848, "rep_idx": 30}, {"w": "yxYxYXX", "n": 4, "status": "19_14", "ms_idx": 819, "rep_idx": 63}, {"w": "yxYxYXX", "n": 5, "status": "21_13", "ms_idx": 707, "rep_idx": 104}, {"w": "yxYxYXX", "n": 6, "status": "23_8", "ms_idx": 821, "rep_idx": 157}, {"w": "yxYxYXX", "n": 7, "status": "25_14", "ms_idx": 1087, "rep_idx": 227}, {"w": "yxYxyXX", "n": 1, "status": "trivial", "ms_idx": 91}, {"w": "yxYxyXX", "n": 2, "status": "15_8", "ms_idx": 1151, "rep_idx": 13}, {"w": "yxYxyXX", "n": 3, "status": "17_14", "ms_idx": 974, "rep_idx": 29}, {"w": "yxYxyXX", "n": 4, "status": "19_13", "ms_idx": 938, "rep_idx": 62}, {"w": "yxYxyXX", "n": 5, "status": "21_12", "ms_idx": 906, "rep_idx": 103}, {"w": "yxYxyXX", "n": 6, "status": "23_7", "ms_idx": 914, "rep_idx": 156}, {"w": "yxYxyXX", "n": 7, "status": "25_13", "ms_idx": 996, "rep_idx": 226}, {"w": "yxyxYXX", "n": 1, "status": "trivial", "ms_idx": 83}, {"w": "yxyxYXX", "n": 2, "status": "15_7", "ms_idx": 677, "rep_idx": 12}, {"w": "yxyxYXX", "n": 3, "status": "17_13", "ms_idx": 1169, "rep_idx": 28}, {"w": "yxyxYXX", "n": 4, "status": "19_12", "ms_idx": 814, "rep_idx": 61}, {"w": "yxyxYXX", "n": 5, "status": "21_11", "ms_idx": 661, "rep_idx": 102}, {"w": "yxyxYXX", "n": 6, "status": "23_6", "ms_idx": 1141, "rep_idx": 155}, {"w": "yxyxYXX", "n": 7, "status": "25_12", "ms_idx": 1043, "rep_idx": 224}, {"w": "yxyxyXX", "n": 1, "status": "trivial", "ms_idx": 82}, {"w": "yxyxyXX", "n": 2, "status": "15_6", "ms_idx": 1028, "rep_idx": 11}, {"w": "yxyxyXX", "n": 3, "status": "17_12", "ms_idx": 913, "rep_idx": 27}, {"w": "yxyxyXX", "n": 4, "status": "19_11", "ms_idx": 966, "rep_idx": 60}, {"w": "yxyxyXX", "n": 5, "status": "21_10", "ms_idx": 1173, "rep_idx": 101}, {"w": "yxyxyXX", "n": 6, "status": "23_5", "ms_idx": 1089, "rep_idx": 154}, {"w": "yxyxyXX", "n": 7, "status": "25_11", "ms_idx": 771, "rep_idx": 223}, {"w": "yXYxxYX", "n": 1, "status": "trivial", "ms_idx": 130}, {"w": "yXYxxYX", "n": 2, "status": "14_2", "ms_idx": 948, "rep_idx": 6}, {"w": "yXYxxYX", "n": 3, "status": "17_17", "ms_idx": 1051, "rep_idx": 32}, {"w": "yXYxxYX", "n": 4, "status": "19_20", "ms_idx": 1148, "rep_idx": 69}, {"w": "yXYxxYX", "n": 5, "status": "21_18", "ms_idx": 1099, "rep_idx": 110}, {"w": "yXYxxYX", "n": 6, "status": "22_10", "ms_idx": 903, "rep_idx": 165}, {"w": "yXYxxYX", "n": 7, "status": "25_20", "ms_idx": 969, "rep_idx": 242}, {"w": "yXYxxyX", "n": 1, "status": "trivial", "ms_idx": 129}, {"w": "yXYxxyX", "n": 2, "status": "14_1", "ms_idx": 1047, "rep_idx": 5}, {"w": "yXYxxyX", "n": 3, "status": "17_16", "ms_idx": 675, "rep_idx": 31}, {"w": "yXYxxyX", "n": 4, "status": "19_19", "ms_idx": 748, "rep_idx": 68}, {"w": "yXYxxyX", "n": 5, "status": "21_17", "ms_idx": 937, "rep_idx": 109}, {"w": "yXYxxyX", "n": 6, "status": "22_9", "ms_idx": 810, "rep_idx": 164}, {"w": "yXYxxyX", "n": 7, "status": "25_19", "ms_idx": 889, "rep_idx": 241}, {"w": "yxxYYXX", "n": 1, "status": "trivial", "ms_idx": 81}, {"w": "yxxYYXX", "n": 2, "status": "15_3", "ms_idx": 655, "rep_idx": 8}, {"w": "yxxYYXX", "n": 3, "status": "17_11", "ms_idx": 920, "rep_idx": 26}, {"w": "yxxYYXX", "n": 4, "status": "19_10", "ms_idx": 1160, "rep_idx": 59}, {"w": "yxxYYXX", "n": 5, "status": "21_9", "ms_idx": 943, "rep_idx": 100}, {"w": "yxxYYXX", "n": 6, "status": "23_4", "ms_idx": 1022, "rep_idx": 153}, {"w": "yxxYYXX", "n": 7, "status": "25_10", "ms_idx": 1097, "rep_idx": 222}, {"w": "yxxyyXX", "n": 1, "status": "trivial", "ms_idx": 72}, {"w": "yxxyyXX", "n": 2, "status": "15_2", "ms_idx": 1027, "rep_idx": 7}, {"w": "yxxyyXX", "n": 3, "status": "17_2", "ms_idx": 912, "rep_idx": 17}, {"w": "yxxyyXX", "n": 4, "status": "19_1", "ms_idx": 964, "rep_idx": 50}, {"w": "yxxyyXX", "n": 5, "status": "21_2", "ms_idx": 1172, "rep_idx": 91}, {"w": "yxxyyXX", "n": 6, "status": "23_1", "ms_idx": 1090, "rep_idx": 144}, {"w": "yxxyyXX", "n": 7, "status": "25_1", "ms_idx": 767, "rep_idx": 213}, {"w": "yxxYXYX", "n": 1, "status": "trivial", "ms_idx": 80}, {"w": "yxxYXYX", "n": 2, "status": "15_2", "ms_idx": 653, "rep_idx": 7}, {"w": "yxxYXYX", "n": 3, "status": "17_10", "ms_idx": 918, "rep_idx": 25}, {"w": "yxxYXYX", "n": 4, "status": "19_9", "ms_idx": 1159, "rep_idx": 58}, {"w": "yxxYXYX", "n": 5, "status": "20_5", "ms_idx": 942, "rep_idx": 99}, {"w": "yxxYXYX", "n": 6, "status": "21_31", "ms_idx": 1023, "rep_idx": 152}, {"w": "yxxYXYX", "n": 7, "status": "25_9", "ms_idx": 1095, "rep_idx": 221}, {"w": "yxxYXyX", "n": 1, "status": "trivial", "ms_idx": 77}, {"w": "yxxYXyX", "n": 2, "status": "15_5", "ms_idx": 726, "rep_idx": 10}, {"w": "yxxYXyX", "n": 3, "status": "17_7", "ms_idx": 1002, "rep_idx": 22}, {"w": "yxxYXyX", "n": 4, "status": "19_6", "ms_idx": 896, "rep_idx": 55}, {"w": "yxxYXyX", "n": 5, "status": "21_6", "ms_idx": 843, "rep_idx": 96}, {"w": "yxxYXyX", "n": 6, "status": "23_3", "ms_idx": 826, "rep_idx": 149}, {"w": "yxxYXyX", "n": 7, "status": "25_6", "ms_idx": 1150, "rep_idx": 218}, {"w": "yxxyXYX", "n": 1, "status": "trivial", "ms_idx": 76}, {"w": "yxxyXYX", "n": 2, "status": "15_4", "ms_idx": 975, "rep_idx": 9}, {"w": "yxxyXYX", "n": 3, "status": "17_6", "ms_idx": 1020, "rep_idx": 21}, {"w": "yxxyXYX", "n": 4, "status": "19_5", "ms_idx": 663, "rep_idx": 54}, {"w": "yxxyXYX", "n": 5, "status": "21_5", "ms_idx": 886, "rep_idx": 95}, {"w": "yxxyXYX", "n": 6, "status": "23_2", "ms_idx": 682, "rep_idx": 148}, {"w": "yxxyXYX", "n": 7, "status": "25_5", "ms_idx": 749, "rep_idx": 217}, {"w": "yxxyXyX", "n": 1, "status": "trivial", "ms_idx": 73}, {"w": "yxxyXyX", "n": 2, "status": "15_3", "ms_idx": 647, "rep_idx": 8}, {"w": "yxxyXyX", "n": 3, "status": "17_3", "ms_idx": 980, "rep_idx": 18}, {"w": "yxxyXyX", "n": 4, "status": "19_2", "ms_idx": 1152, "rep_idx": 51}, {"w": "yxxyXyX", "n": 5, "status": "20_4", "ms_idx": 946, "rep_idx": 92}, {"w": "yxxyXyX", "n": 6, "status": "21_30", "ms_idx": 972, "rep_idx": 145}, {"w": "yxxyXyX", "n": 7, "status": "25_2", "ms_idx": 1134, "rep_idx": 214}, {"w": "yXXYxxY", "n": 1, "status": "trivial", "ms_idx": 128}, {"w": "yXXYxxY", "n": 2, "status": "15_7", "ms_idx": 1077, "rep_idx": 12}, {"w": "yXXYxxY", "n": 3, "status": "17_19", "ms_idx": 960, "rep_idx": 34}, {"w": "yXXYxxY", "n": 4, "status": "19_18", "ms_idx": 1048, "rep_idx": 67}, {"w": "yXXYxxY", "n": 5, "status": "21_16", "ms_idx": 971, "rep_idx": 108}, {"w": "yXXYxxY", "n": 6, "status": "23_11", "ms_idx": 1120, "rep_idx": 163}, {"w": "yXXYxxY", "n": 7, "status": "25_18", "ms_idx": 1139, "rep_idx": 240}, {"w": "yXXYxxy", "n": 1, "status": "trivial", "ms_idx": 127}, {"w": "yXXYxxy", "n": 2, "status": "15_6", "ms_idx": 744, "rep_idx": 11}, {"w": "yXXYxxy", "n": 3, "status": "17_18", "ms_idx": 638, "rep_idx": 33}, {"w": "yXXYxxy", "n": 4, "status": "19_17", "ms_idx": 979, "rep_idx": 66}, {"w": "yXXYxxy", "n": 5, "status": "20_6", "ms_idx": 733, "rep_idx": 107}, {"w": "yXXYxxy", "n": 6, "status": "21_32", "ms_idx": 1176, "rep_idx": 162}, {"w": "yXXYxxy", "n": 7, "status": "25_17", "ms_idx": 746, "rep_idx": 239}, {"w": "yxxYXXY", "n": 1, "status": "trivial", "ms_idx": 79}, {"w": "yxxYXXY", "n": 2, "status": "14_1", "ms_idx": 652, "rep_idx": 5}, {"w": "yxxYXXY", "n": 3, "status": "17_9", "ms_idx": 917, "rep_idx": 24}, {"w": "yxxYXXY", "n": 4, "status": "19_8", "ms_idx": 1156, "rep_idx": 57}, {"w": "yxxYXXY", "n": 5, "status": "21_8", "ms_idx": 941, "rep_idx": 98}, {"w": "yxxYXXY", "n": 6, "status": "22_8", "ms_idx": 1021, "rep_idx": 151}, {"w": "yxxYXXY", "n": 7, "status": "25_8", "ms_idx": 1096, "rep_idx": 220}, {"w": "yxxYXXy", "n": 1, "status": "trivial", "ms_idx": 78}, {"w": "yxxYXXy", "n": 2, "status": "14_1", "ms_idx": 817, "rep_idx": 5}, {"w": "yxxYXXy", "n": 3, "status": "17_8", "ms_idx": 1140, "rep_idx": 23}, {"w": "yxxYXXy", "n": 4, "status": "19_7", "ms_idx": 681, "rep_idx": 56}, {"w": "yxxYXXy", "n": 5, "status": "21_7", "ms_idx": 742, "rep_idx": 97}, {"w": "yxxYXXy", "n": 6, "status": "22_7", "ms_idx": 931, "rep_idx": 150}, {"w": "yxxYXXy", "n": 7, "status": "25_7", "ms_idx": 1057, "rep_idx": 219}, {"w": "yxxyXXY", "n": 1, "status": "trivial", "ms_idx": 75}, {"w": "yxxyXXY", "n": 2, "status": "14_2", "ms_idx": 773, "rep_idx": 6}, {"w": "yxxyXXY", "n": 3, "status": "17_5", "ms_idx": 1000, "rep_idx": 20}, {"w": "yxxyXXY", "n": 4, "status": "19_4", "ms_idx": 1045, "rep_idx": 53}, {"w": "yxxyXXY", "n": 5, "status": "21_4", "ms_idx": 1076, "rep_idx": 94}, {"w": "yxxyXXY", "n": 6, "status": "22_6", "ms_idx": 859, "rep_idx": 147}, {"w": "yxxyXXY", "n": 7, "status": "25_4", "ms_idx": 1121, "rep_idx": 216}, {"w": "yxxyXXy", "n": 1, "status": "trivial", "ms_idx": 74}, {"w": "yxxyXXy", "n": 2, "status": "14_2", "ms_idx": 751, "rep_idx": 6}, {"w": "yxxyXXy", "n": 3, "status": "17_4", "ms_idx": 840, "rep_idx": 19}, {"w": "yxxyXXy", "n": 4, "status": "19_3", "ms_idx": 1147, "rep_idx": 52}, {"w": "yxxyXXy", "n": 5, "status": "21_3", "ms_idx": 779, "rep_idx": 93}, {"w": "yxxyXXy", "n": 6, "status": "22_5", "ms_idx": 705, "rep_idx": 146}, {"w": "yxxyXXy", "n": 7, "status": "25_3", "ms_idx": 825, "rep_idx": 215}, {"w": "XYYYYxY", "n": 1, "status": "trivial", "ms_idx": 156}, {"w": "XYYYYxY", "n": 2, "status": "trivial", "ms_idx": 294}, {"w": "XYYYYxY", "n": 3, "status": "13_1", "ms_idx": 715, "rep_idx": 0}, {"w": "XYYYYxY", "n": 4, "status": "trivial", "ms_idx": 455}, {"w": "XYYYYxY", "n": 5, "status": "trivial", "ms_idx": 586}, {"w": "XYYYYxY", "n": 6, "status": "16_7", "ms_idx": 930, "rep_idx": 128}, {"w": "XYYYYxY", "n": 7, "status": "19_52", "ms_idx": 905, "rep_idx": 260}, {"w": "XYYYYxy", "n": 1, "status": "trivial", "ms_idx": 155}, {"w": "XYYYYxy", "n": 2, "status": "trivial", "ms_idx": 293}, {"w": "XYYYYxy", "n": 3, "status": "trivial", "ms_idx": 396}, {"w": "XYYYYxy", "n": 4, "status": "trivial", "ms_idx": 454}, {"w": "XYYYYxy", "n": 5, "status": "16_1", "ms_idx": 933, "rep_idx": 2}, {"w": "XYYYYxy", "n": 6, "status": "16_6", "ms_idx": 845, "rep_idx": 127}, {"w": "XYYYYxy", "n": 7, "status": "19_51", "ms_idx": 1054, "rep_idx": 259}, {"w": "XYYYxYY", "n": 1, "status": "trivial", "ms_idx": 154}, {"w": "XYYYxYY", "n": 2, "status": "trivial", "ms_idx": 292}, {"w": "XYYYxYY", "n": 3, "status": "trivial", "ms_idx": 395}, {"w": "XYYYxYY", "n": 4, "status": "14_1", "ms_idx": 1094, "rep_idx": 5}, {"w": "XYYYxYY", "n": 5, "status": "trivial", "ms_idx": 585}, {"w": "XYYYxYY", "n": 6, "status": "trivial", "ms_idx": 612}, {"w": "XYYYxYY", "n": 7, "status": "21_42", "ms_idx": 952, "rep_idx": 258}, {"w": "XYYYxyy", "n": 1, "status": "trivial", "ms_idx": 153}, {"w": "XYYYxyy", "n": 2, "status": "trivial", "ms_idx": 291}, {"w": "XYYYxyy", "n": 3, "status": "trivial", "ms_idx": 394}, {"w": "XYYYxyy", "n": 4, "status": "15_10", "ms_idx": 1067, "rep_idx": 45}, {"w": "XYYYxyy", "n": 5, "status": "16_4", "ms_idx": 674, "rep_idx": 88}, {"w": "XYYYxyy", "n": 6, "status": "trivial", "ms_idx": 514}, {"w": "XYYYxyy", "n": 7, "status": "19_50", "ms_idx": 809, "rep_idx": 257}, {"w": "XYYxYYY", "n": 1, "status": "trivial", "ms_idx": 152}, {"w": "XYYxYYY", "n": 2, "status": "trivial", "ms_idx": 290}, {"w": "XYYxYYY", "n": 3, "status": "13_1", "ms_idx": 768, "rep_idx": 0}, {"w": "XYYxYYY", "n": 4, "status": "trivial", "ms_idx": 453}, {"w": "XYYxYYY", "n": 5, "status": "trivial", "ms_idx": 489}, {"w": "XYYxYYY", "n": 6, "status": "18_5", "ms_idx": 664, "rep_idx": 178}, {"w": "XYYxYYY", "n": 7, "status": "21_41", "ms_idx": 919, "rep_idx": 256}, {"w": "XYYxyyy", "n": 1, "status": "trivial", "ms_idx": 151}, {"w": "XYYxyyy", "n": 2, "status": "trivial", "ms_idx": 289}, {"w": "XYYxyyy", "n": 3, "status": "trivial", "ms_idx": 393}, {"w": "XYYxyyy", "n": 4, "status": "trivial", "ms_idx": 452}, {"w": "XYYxyyy", "n": 5, "status": "trivial", "ms_idx": 488}, {"w": "XYYxyyy", "n": 6, "status": "trivial", "ms_idx": 955}, {"w": "XYYxyyy", "n": 7, "status": "19_49", "ms_idx": 643, "rep_idx": 255}, {"w": "XYxYYYY", "n": 1, "status": "trivial", "ms_idx": 148}, {"w": "XYxYYYY", "n": 2, "status": "trivial", "ms_idx": 288}, {"w": "XYxYYYY", "n": 3, "status": "trivial", "ms_idx": 392}, {"w": "XYxYYYY", "n": 4, "status": "trivial", "ms_idx": 553}, {"w": "XYxYYYY", "n": 5, "status": "trivial", "ms_idx": 584}, {"w": "XYxYYYY", "n": 6, "status": "17_39", "ms_idx": 660, "rep_idx": 141}, {"w": "XYxYYYY", "n": 7, "status": "trivial", "ms_idx": 632}, {"w": "XYxyyyy", "n": 1, "status": "trivial", "ms_idx": 147}, {"w": "XYxyyyy", "n": 2, "status": "trivial", "ms_idx": 287}, {"w": "XYxyyyy", "n": 3, "status": "trivial", "ms_idx": 391}, {"w": "XYxyyyy", "n": 4, "status": "15_1", "ms_idx": 1157, "rep_idx": 1}, {"w": "XYxyyyy", "n": 5, "status": "14_1", "ms_idx": 944, "rep_idx": 5}, {"w": "XYxyyyy", "n": 6, "status": "17_40", "ms_idx": 1024, "rep_idx": 142}, {"w": "XYxyyyy", "n": 7, "status": "trivial", "ms_idx": 631}, {"w": "XYXYxxY", "n": 1, "status": "trivial", "ms_idx": 150}, {"w": "XYXYxxY", "n": 2, "status": "14_2", "ms_idx": 1158, "rep_idx": 6}, {"w": "XYXYxxY", "n": 3, "status": "17_29", "ms_idx": 808, "rep_idx": 44}, {"w": "XYXYxxY", "n": 4, "status": "19_32", "ms_idx": 849, "rep_idx": 81}, {"w": "XYXYxxY", "n": 5, "status": "21_29", "ms_idx": 797, "rep_idx": 122}, {"w": "XYXYxxY", "n": 6, "status": "22_12", "ms_idx": 894, "rep_idx": 177}, {"w": "XYXYxxY", "n": 7, "status": "25_32", "ms_idx": 880, "rep_idx": 254}, {"w": "XYXYxxy", "n": 1, "status": "trivial", "ms_idx": 149}, {"w": "XYXYxxy", "n": 2, "status": "14_1", "ms_idx": 750, "rep_idx": 5}, {"w": "XYXYxxy", "n": 3, "status": "17_28", "ms_idx": 1078, "rep_idx": 43}, {"w": "XYXYxxy", "n": 4, "status": "19_31", "ms_idx": 649, "rep_idx": 80}, {"w": "XYXYxxy", "n": 5, "status": "21_28", "ms_idx": 1155, "rep_idx": 121}, {"w": "XYXYxxy", "n": 6, "status": "22_11", "ms_idx": 676, "rep_idx": 176}, {"w": "XYXYxxy", "n": 7, "status": "25_31", "ms_idx": 956, "rep_idx": 253}, {"w": "XYxxYXY", "n": 1, "status": "trivial", "ms_idx": 146}, {"w": "XYxxYXY", "n": 2, "status": "15_9", "ms_idx": 724, "rep_idx": 14}, {"w": "XYxxYXY", "n": 3, "status": "17_27", "ms_idx": 737, "rep_idx": 42}, {"w": "XYxxYXY", "n": 4, "status": "19_30", "ms_idx": 784, "rep_idx": 79}, {"w": "XYxxYXY", "n": 5, "status": "20_7", "ms_idx": 907, "rep_idx": 120}, {"w": "XYxxYXY", "n": 6, "status": "21_33", "ms_idx": 1129, "rep_idx": 175}, {"w": "XYxxYXY", "n": 7, "status": "25_30", "ms_idx": 803, "rep_idx": 252}, {"w": "XYxxyXY", "n": 1, "status": "trivial", "ms_idx": 145}, {"w": "XYxxyXY", "n": 2, "status": "15_8", "ms_idx": 730, "rep_idx": 13}, {"w": "XYxxyXY", "n": 3, "status": "17_26", "ms_idx": 983, "rep_idx": 41}, {"w": "XYxxyXY", "n": 4, "status": "19_29", "ms_idx": 680, "rep_idx": 78}, {"w": "XYxxyXY", "n": 5, "status": "21_27", "ms_idx": 811, "rep_idx": 119}, {"w": "XYxxyXY", "n": 6, "status": "23_20", "ms_idx": 1180, "rep_idx": 174}, {"w": "XYxxyXY", "n": 7, "status": "25_29", "ms_idx": 1040, "rep_idx": 251}, {"w": "XXYYxxY", "n": 1, "status": "trivial", "ms_idx": 144}, {"w": "XXYYxxY", "n": 2, "status": "trivial", "ms_idx": 286}, {"w": "XXYYxxY", "n": 3, "status": "17_9", "ms_idx": 1070, "rep_idx": 24}, {"w": "XXYYxxY", "n": 4, "status": "19_28", "ms_idx": 764, "rep_idx": 77}, {"w": "XXYYxxY", "n": 5, "status": "21_26", "ms_idx": 754, "rep_idx": 118}, {"w": "XXYYxxY", "n": 6, "status": "23_19", "ms_idx": 1154, "rep_idx": 173}, {"w": "XXYYxxY", "n": 7, "status": "25_28", "ms_idx": 978, "rep_idx": 250}, {"w": "XXYYxxy", "n": 1, "status": "trivial", "ms_idx": 143}, {"w": "XXYYxxy", "n": 2, "status": "trivial", "ms_idx": 285}, {"w": "XXYYxxy", "n": 3, "status": "17_5", "ms_idx": 714, "rep_idx": 20}, {"w": "XXYYxxy", "n": 4, "status": "19_27", "ms_idx": 1183, "rep_idx": 76}, {"w": "XXYYxxy", "n": 5, "status": "21_25", "ms_idx": 981, "rep_idx": 117}, {"w": "XXYYxxy", "n": 6, "status": "23_18", "ms_idx": 761, "rep_idx": 172}, {"w": "XXYYxxy", "n": 7, "status": "25_27", "ms_idx": 791, "rep_idx": 249}, {"w": "XXYxYxY", "n": 1, "status": "trivial", "ms_idx": 142}, {"w": "XXYxYxY", "n": 2, "status": "15_2", "ms_idx": 900, "rep_idx": 7}, {"w": "XXYxYxY", "n": 3, "status": "17_25", "ms_idx": 1073, "rep_idx": 40}, {"w": "XXYxYxY", "n": 4, "status": "19_26", "ms_idx": 1050, "rep_idx": 75}, {"w": "XXYxYxY", "n": 5, "status": "21_24", "ms_idx": 963, "rep_idx": 116}, {"w": "XXYxYxY", "n": 6, "status": "23_17", "ms_idx": 659, "rep_idx": 171}, {"w": "XXYxYxY", "n": 7, "status": "25_26", "ms_idx": 712, "rep_idx": 248}, {"w": "XXYxYxy", "n": 1, "status": "trivial", "ms_idx": 141}, {"w": "XXYxYxy", "n": 2, "status": "15_4", "ms_idx": 926, "rep_idx": 9}, {"w": "XXYxYxy", "n": 3, "status": "17_24", "ms_idx": 683, "rep_idx": 39}, {"w": "XXYxYxy", "n": 4, "status": "19_25", "ms_idx": 1056, "rep_idx": 74}, {"w": "XXYxYxy", "n": 5, "status": "21_23", "ms_idx": 701, "rep_idx": 115}, {"w": "XXYxYxy", "n": 6, "status": "23_16", "ms_idx": 976, "rep_idx": 170}, {"w": "XXYxYxy", "n": 7, "status": "25_25", "ms_idx": 1029, "rep_idx": 247}, {"w": "XXYxyxY", "n": 1, "status": "trivial", "ms_idx": 140}, {"w": "XXYxyxY", "n": 2, "status": "15_5", "ms_idx": 902, "rep_idx": 10}, {"w": "XXYxyxY", "n": 3, "status": "17_23", "ms_idx": 723, "rep_idx": 38}, {"w": "XXYxyxY", "n": 4, "status": "19_24", "ms_idx": 1082, "rep_idx": 73}, {"w": "XXYxyxY", "n": 5, "status": "21_22", "ms_idx": 1131, "rep_idx": 114}, {"w": "XXYxyxY", "n": 6, "status": "23_15", "ms_idx": 672, "rep_idx": 169}, {"w": "XXYxyxY", "n": 7, "status": "25_24", "ms_idx": 1112, "rep_idx": 246}, {"w": "XXYxyxy", "n": 1, "status": "trivial", "ms_idx": 139}, {"w": "XXYxyxy", "n": 2, "status": "15_3", "ms_idx": 690, "rep_idx": 8}, {"w": "XXYxyxy", "n": 3, "status": "17_22", "ms_idx": 987, "rep_idx": 37}, {"w": "XXYxyxy", "n": 4, "status": "19_23", "ms_idx": 1171, "rep_idx": 72}, {"w": "XXYxyxy", "n": 5, "status": "21_21", "ms_idx": 1026, "rep_idx": 113}, {"w": "XXYxyxy", "n": 6, "status": "23_14", "ms_idx": 991, "rep_idx": 168}, {"w": "XXYxyxy", "n": 7, "status": "25_23", "ms_idx": 720, "rep_idx": 245}, {"w": "XXYxxYY", "n": 1, "status": "trivial", "ms_idx": 138}, {"w": "XXYxxYY", "n": 2, "status": "15_6", "ms_idx": 725, "rep_idx": 11}, {"w": "XXYxxYY", "n": 3, "status": "17_21", "ms_idx": 736, "rep_idx": 36}, {"w": "XXYxxYY", "n": 4, "status": "19_22", "ms_idx": 785, "rep_idx": 71}, {"w": "XXYxxYY", "n": 5, "status": "21_20", "ms_idx": 910, "rep_idx": 112}, {"w": "XXYxxYY", "n": 6, "status": "23_13", "ms_idx": 1127, "rep_idx": 167}, {"w": "XXYxxYY", "n": 7, "status": "25_22", "ms_idx": 801, "rep_idx": 244}, {"w": "XXYxxyy", "n": 1, "status": "trivial", "ms_idx": 137}, {"w": "XXYxxyy", "n": 2, "status": "15_9", "ms_idx": 689, "rep_idx": 14}, {"w": "XXYxxyy", "n": 3, "status": "17_20", "ms_idx": 986, "rep_idx": 35}, {"w": "XXYxxyy", "n": 4, "status": "19_21", "ms_idx": 1168, "rep_idx": 70}, {"w": "XXYxxyy", "n": 5, "status": "21_19", "ms_idx": 1025, "rep_idx": 111}, {"w": "XXYxxyy", "n": 6, "status": "23_12", "ms_idx": 990, "rep_idx": 166}, {"w": "XXYxxyy", "n": 7, "status": "25_21", "ms_idx": 719, "rep_idx": 243}]}
